{
  "domain": "serbia.news-pravda.com",
  "totalArticles": 424,
  "articlesPerDay": [
    {
      "date": "2025-04-23",
      "count": 128
    },
    {
      "date": "2025-04-24",
      "count": 296
    }
  ],
  "topSources": [
    {
      "source": "rt.rs",
      "count": 77
    },
    {
      "source": "sputnikportal.rs",
      "count": 60
    },
    {
      "source": "Telegram: sputniksrbija",
      "count": 43
    },
    {
      "source": "Telegram: istocni_front",
      "count": 39
    },
    {
      "source": "Telegram: SrbijaRusija",
      "count": 36
    },
    {
      "source": "Telegram: rtbalkan",
      "count": 32
    },
    {
      "source": "Telegram: ukr_leaks_srb",
      "count": 25
    },
    {
      "source": "Telegram: debeljaca1vrs",
      "count": 18
    },
    {
      "source": "Telegram: silasaistoka",
      "count": 14
    },
    {
      "source": "srb.news-front.su",
      "count": 10
    },
    {
      "source": "Telegram: BunkerSrb",
      "count": 10
    },
    {
      "source": "Telegram: RepublikaSrpska22",
      "count": 9
    },
    {
      "source": "Telegram: borbeni_efektivi",
      "count": 4
    },
    {
      "source": "ria.ru",
      "count": 4
    },
    {
      "source": "tass.ru",
      "count": 4
    },
    {
      "source": "Telegram: dobrojutrozemljomoja",
      "count": 4
    },
    {
      "source": "Telegram: Politnavigator",
      "count": 3
    },
    {
      "source": "Telegram: drustveni_udar",
      "count": 2
    },
    {
      "source": "Telegram: vestniksrb",
      "count": 2
    },
    {
      "source": "Telegram: russkydomserbia",
      "count": 2
    },
    {
      "source": "Telegram: SerbiaRussia",
      "count": 2
    },
    {
      "source": "Telegram: InfoDefSERBIA",
      "count": 2
    },
    {
      "source": "Telegram: pepopolitika",
      "count": 1
    },
    {
      "source": "Telegram: rtbalkan_ru",
      "count": 1
    },
    {
      "source": "Telegram: russkydombelgrad",
      "count": 1
    },
    {
      "source": "Telegram: ukr_2025_ru",
      "count": 1
    },
    {
      "source": "Telegram: lomovkaa",
      "count": 1
    },
    {
      "source": "lenta.ru",
      "count": 1
    },
    {
      "source": "Telegram: faktorga",
      "count": 1
    },
    {
      "source": "Telegram: ostashkonews",
      "count": 1
    },
    {
      "source": "Telegram: vaseljenskars",
      "count": 1
    },
    {
      "source": "Telegram: lokalitetvesti",
      "count": 1
    },
    {
      "source": "Telegram: zvezdanews",
      "count": 1
    },
    {
      "source": "kianews24.ru",
      "count": 1
    },
    {
      "source": "Telegram: radio_sputnik",
      "count": 1
    },
    {
      "source": "gazetacrimea.ru",
      "count": 1
    },
    {
      "source": "Telegram: ruserbia",
      "count": 1
    },
    {
      "source": "Telegram: olga_b_lyubimova",
      "count": 1
    },
    {
      "source": "Telegram: tass_world",
      "count": 1
    },
    {
      "source": "Telegram: MidRusEvrazes",
      "count": 1
    },
    {
      "source": "Telegram: rusembserbia",
      "count": 1
    },
    {
      "source": "Telegram: buntcg",
      "count": 1
    },
    {
      "source": "Telegram: Gorchakov_Fund",
      "count": 1
    },
    {
      "source": "Telegram: rybar",
      "count": 1
    }
  ],
  "categories": [
    {
      "category": "world",
      "count": 345
    },
    {
      "category": "serbia",
      "count": 79
    }
  ],
  "publicationHours": [
    {
      "hour": 0,
      "count": 1
    },
    {
      "hour": 1,
      "count": 1
    },
    {
      "hour": 2,
      "count": 2
    },
    {
      "hour": 3,
      "count": 2
    },
    {
      "hour": 4,
      "count": 10
    },
    {
      "hour": 5,
      "count": 19
    },
    {
      "hour": 6,
      "count": 22
    },
    {
      "hour": 7,
      "count": 30
    },
    {
      "hour": 8,
      "count": 31
    },
    {
      "hour": 9,
      "count": 47
    },
    {
      "hour": 10,
      "count": 41
    },
    {
      "hour": 11,
      "count": 43
    },
    {
      "hour": 12,
      "count": 27
    },
    {
      "hour": 13,
      "count": 19
    },
    {
      "hour": 14,
      "count": 14
    },
    {
      "hour": 15,
      "count": 22
    },
    {
      "hour": 16,
      "count": 20
    },
    {
      "hour": 17,
      "count": 23
    },
    {
      "hour": 18,
      "count": 16
    },
    {
      "hour": 19,
      "count": 6
    },
    {
      "hour": 20,
      "count": 4
    },
    {
      "hour": 21,
      "count": 15
    },
    {
      "hour": 22,
      "count": 5
    },
    {
      "hour": 23,
      "count": 4
    }
  ],
  "sourcesByDay": [
    {
      "date": "2025-04-23",
      "rt.rs": 23,
      "sputnikportal.rs": 15,
      "Telegram: sputniksrbija": 14,
      "Telegram: istocni_front": 17,
      "Telegram: SrbijaRusija": 9,
      "Telegram: rtbalkan": 8,
      "Telegram: ukr_leaks_srb": 9,
      "Telegram: debeljaca1vrs": 9,
      "Telegram: silasaistoka": 3,
      "srb.news-front.su": 3
    },
    {
      "date": "2025-04-24",
      "rt.rs": 54,
      "sputnikportal.rs": 45,
      "Telegram: sputniksrbija": 29,
      "Telegram: istocni_front": 22,
      "Telegram: SrbijaRusija": 27,
      "Telegram: rtbalkan": 24,
      "Telegram: ukr_leaks_srb": 16,
      "Telegram: debeljaca1vrs": 9,
      "Telegram: silasaistoka": 11,
      "srb.news-front.su": 7
    }
  ],
  "topSourceNames": [
    "rt.rs",
    "sputnikportal.rs",
    "Telegram: sputniksrbija",
    "Telegram: istocni_front",
    "Telegram: SrbijaRusija",
    "Telegram: rtbalkan",
    "Telegram: ukr_leaks_srb",
    "Telegram: debeljaca1vrs",
    "Telegram: silasaistoka",
    "srb.news-front.su"
  ],
  "alternatesStats": {
    "articlesWithAlternates": 41,
    "percentWithAlternates": 9.669811320754718,
    "avgAlternatesPerArticle": 5.536585365853658
  },
  "languages": [
    {
      "language": "en",
      "count": 94
    },
    {
      "language": "sr",
      "count": 81
    },
    {
      "language": "bs",
      "count": 17
    },
    {
      "language": "de",
      "count": 4
    },
    {
      "language": "sq",
      "count": 3
    },
    {
      "language": "it",
      "count": 3
    },
    {
      "language": "es",
      "count": 3
    },
    {
      "language": "lv",
      "count": 3
    },
    {
      "language": "fi",
      "count": 3
    },
    {
      "language": "uk",
      "count": 2
    },
    {
      "language": "el",
      "count": 2
    },
    {
      "language": "fr",
      "count": 2
    },
    {
      "language": "nl",
      "count": 2
    },
    {
      "language": "hy",
      "count": 1
    },
    {
      "language": "sk",
      "count": 1
    },
    {
      "language": "ro",
      "count": 1
    },
    {
      "language": "ar",
      "count": 1
    },
    {
      "language": "tr",
      "count": 1
    },
    {
      "language": "et",
      "count": 1
    },
    {
      "language": "lt",
      "count": 1
    },
    {
      "language": "hr",
      "count": 1
    }
  ],
  "languageConnections": [
    {
      "source": "sr",
      "target": "en",
      "strength": 28
    },
    {
      "source": "sr",
      "target": "bs",
      "strength": 10
    },
    {
      "source": "sr",
      "target": "sq",
      "strength": 3
    },
    {
      "source": "sr",
      "target": "it",
      "strength": 3
    },
    {
      "source": "sr",
      "target": "es",
      "strength": 3
    },
    {
      "source": "sr",
      "target": "lv",
      "strength": 3
    },
    {
      "source": "sr",
      "target": "fi",
      "strength": 3
    },
    {
      "source": "sr",
      "target": "uk",
      "strength": 2
    },
    {
      "source": "sr",
      "target": "el",
      "strength": 2
    },
    {
      "source": "sr",
      "target": "de",
      "strength": 2
    },
    {
      "source": "sr",
      "target": "sk",
      "strength": 1
    },
    {
      "source": "sr",
      "target": "hy",
      "strength": 1
    },
    {
      "source": "sr",
      "target": "ro",
      "strength": 1
    },
    {
      "source": "sr",
      "target": "ar",
      "strength": 1
    },
    {
      "source": "sr",
      "target": "tr",
      "strength": 1
    },
    {
      "source": "sr",
      "target": "fr",
      "strength": 1
    },
    {
      "source": "sr",
      "target": "nl",
      "strength": 1
    },
    {
      "source": "sr",
      "target": "et",
      "strength": 1
    },
    {
      "source": "sr",
      "target": "lt",
      "strength": 1
    },
    {
      "source": "sr",
      "target": "hr",
      "strength": 1
    },
    {
      "source": "en",
      "target": "sr",
      "strength": 28
    },
    {
      "source": "en",
      "target": "bs",
      "strength": 10
    },
    {
      "source": "en",
      "target": "sq",
      "strength": 3
    },
    {
      "source": "en",
      "target": "it",
      "strength": 3
    },
    {
      "source": "en",
      "target": "es",
      "strength": 3
    },
    {
      "source": "en",
      "target": "lv",
      "strength": 3
    },
    {
      "source": "en",
      "target": "fi",
      "strength": 3
    },
    {
      "source": "en",
      "target": "uk",
      "strength": 2
    },
    {
      "source": "en",
      "target": "el",
      "strength": 2
    },
    {
      "source": "en",
      "target": "de",
      "strength": 2
    },
    {
      "source": "en",
      "target": "sk",
      "strength": 1
    },
    {
      "source": "en",
      "target": "hy",
      "strength": 1
    },
    {
      "source": "en",
      "target": "ro",
      "strength": 1
    },
    {
      "source": "en",
      "target": "ar",
      "strength": 1
    },
    {
      "source": "en",
      "target": "tr",
      "strength": 1
    },
    {
      "source": "en",
      "target": "fr",
      "strength": 1
    },
    {
      "source": "en",
      "target": "nl",
      "strength": 1
    },
    {
      "source": "en",
      "target": "et",
      "strength": 1
    },
    {
      "source": "en",
      "target": "lt",
      "strength": 1
    },
    {
      "source": "en",
      "target": "hr",
      "strength": 1
    },
    {
      "source": "uk",
      "target": "sr",
      "strength": 2
    },
    {
      "source": "uk",
      "target": "en",
      "strength": 2
    },
    {
      "source": "uk",
      "target": "sk",
      "strength": 1
    },
    {
      "source": "uk",
      "target": "hy",
      "strength": 1
    },
    {
      "source": "sk",
      "target": "en",
      "strength": 1
    },
    {
      "source": "sk",
      "target": "uk",
      "strength": 1
    },
    {
      "source": "sk",
      "target": "sr",
      "strength": 1
    },
    {
      "source": "sk",
      "target": "hy",
      "strength": 1
    },
    {
      "source": "hy",
      "target": "en",
      "strength": 1
    },
    {
      "source": "hy",
      "target": "uk",
      "strength": 1
    },
    {
      "source": "hy",
      "target": "sr",
      "strength": 1
    },
    {
      "source": "hy",
      "target": "sk",
      "strength": 1
    },
    {
      "source": "bs",
      "target": "sr",
      "strength": 10
    },
    {
      "source": "bs",
      "target": "en",
      "strength": 10
    },
    {
      "source": "bs",
      "target": "sq",
      "strength": 1
    },
    {
      "source": "bs",
      "target": "de",
      "strength": 1
    },
    {
      "source": "sq",
      "target": "sr",
      "strength": 3
    },
    {
      "source": "sq",
      "target": "en",
      "strength": 3
    },
    {
      "source": "sq",
      "target": "bs",
      "strength": 1
    },
    {
      "source": "sq",
      "target": "tr",
      "strength": 1
    },
    {
      "source": "sq",
      "target": "hr",
      "strength": 1
    },
    {
      "source": "ro",
      "target": "sr",
      "strength": 1
    },
    {
      "source": "ro",
      "target": "en",
      "strength": 1
    },
    {
      "source": "el",
      "target": "en",
      "strength": 2
    },
    {
      "source": "el",
      "target": "sr",
      "strength": 2
    },
    {
      "source": "el",
      "target": "it",
      "strength": 2
    },
    {
      "source": "el",
      "target": "es",
      "strength": 2
    },
    {
      "source": "it",
      "target": "en",
      "strength": 3
    },
    {
      "source": "it",
      "target": "sr",
      "strength": 3
    },
    {
      "source": "it",
      "target": "es",
      "strength": 3
    },
    {
      "source": "it",
      "target": "el",
      "strength": 2
    },
    {
      "source": "it",
      "target": "ar",
      "strength": 1
    },
    {
      "source": "es",
      "target": "en",
      "strength": 3
    },
    {
      "source": "es",
      "target": "sr",
      "strength": 3
    },
    {
      "source": "es",
      "target": "it",
      "strength": 3
    },
    {
      "source": "es",
      "target": "el",
      "strength": 2
    },
    {
      "source": "es",
      "target": "ar",
      "strength": 1
    },
    {
      "source": "de",
      "target": "sr",
      "strength": 2
    },
    {
      "source": "de",
      "target": "en",
      "strength": 2
    },
    {
      "source": "de",
      "target": "bs",
      "strength": 1
    },
    {
      "source": "de",
      "target": "lv",
      "strength": 1
    },
    {
      "source": "de",
      "target": "nl",
      "strength": 1
    },
    {
      "source": "de",
      "target": "et",
      "strength": 1
    },
    {
      "source": "de",
      "target": "lt",
      "strength": 1
    },
    {
      "source": "de",
      "target": "fi",
      "strength": 1
    },
    {
      "source": "lv",
      "target": "sr",
      "strength": 3
    },
    {
      "source": "lv",
      "target": "fi",
      "strength": 3
    },
    {
      "source": "lv",
      "target": "en",
      "strength": 3
    },
    {
      "source": "lv",
      "target": "nl",
      "strength": 1
    },
    {
      "source": "lv",
      "target": "de",
      "strength": 1
    },
    {
      "source": "lv",
      "target": "et",
      "strength": 1
    },
    {
      "source": "lv",
      "target": "lt",
      "strength": 1
    },
    {
      "source": "fi",
      "target": "sr",
      "strength": 3
    },
    {
      "source": "fi",
      "target": "lv",
      "strength": 3
    },
    {
      "source": "fi",
      "target": "en",
      "strength": 3
    },
    {
      "source": "fi",
      "target": "nl",
      "strength": 1
    },
    {
      "source": "fi",
      "target": "de",
      "strength": 1
    },
    {
      "source": "fi",
      "target": "et",
      "strength": 1
    },
    {
      "source": "fi",
      "target": "lt",
      "strength": 1
    },
    {
      "source": "ar",
      "target": "en",
      "strength": 1
    },
    {
      "source": "ar",
      "target": "sr",
      "strength": 1
    },
    {
      "source": "ar",
      "target": "it",
      "strength": 1
    },
    {
      "source": "ar",
      "target": "es",
      "strength": 1
    },
    {
      "source": "tr",
      "target": "sr",
      "strength": 1
    },
    {
      "source": "tr",
      "target": "sq",
      "strength": 1
    },
    {
      "source": "tr",
      "target": "en",
      "strength": 1
    },
    {
      "source": "fr",
      "target": "sr",
      "strength": 1
    },
    {
      "source": "fr",
      "target": "en",
      "strength": 1
    },
    {
      "source": "nl",
      "target": "lv",
      "strength": 1
    },
    {
      "source": "nl",
      "target": "en",
      "strength": 1
    },
    {
      "source": "nl",
      "target": "sr",
      "strength": 1
    },
    {
      "source": "nl",
      "target": "de",
      "strength": 1
    },
    {
      "source": "nl",
      "target": "et",
      "strength": 1
    },
    {
      "source": "nl",
      "target": "lt",
      "strength": 1
    },
    {
      "source": "nl",
      "target": "fi",
      "strength": 1
    },
    {
      "source": "et",
      "target": "lv",
      "strength": 1
    },
    {
      "source": "et",
      "target": "nl",
      "strength": 1
    },
    {
      "source": "et",
      "target": "en",
      "strength": 1
    },
    {
      "source": "et",
      "target": "sr",
      "strength": 1
    },
    {
      "source": "et",
      "target": "de",
      "strength": 1
    },
    {
      "source": "et",
      "target": "lt",
      "strength": 1
    },
    {
      "source": "et",
      "target": "fi",
      "strength": 1
    },
    {
      "source": "lt",
      "target": "lv",
      "strength": 1
    },
    {
      "source": "lt",
      "target": "nl",
      "strength": 1
    },
    {
      "source": "lt",
      "target": "en",
      "strength": 1
    },
    {
      "source": "lt",
      "target": "sr",
      "strength": 1
    },
    {
      "source": "lt",
      "target": "de",
      "strength": 1
    },
    {
      "source": "lt",
      "target": "et",
      "strength": 1
    },
    {
      "source": "lt",
      "target": "fi",
      "strength": 1
    },
    {
      "source": "hr",
      "target": "sr",
      "strength": 1
    },
    {
      "source": "hr",
      "target": "sq",
      "strength": 1
    },
    {
      "source": "hr",
      "target": "en",
      "strength": 1
    }
  ],
  "domainLanguageData": [
    {
      "domain": "balkan.news-pravda.com",
      "language": "en",
      "count": 21
    },
    {
      "domain": "balkan.news-pravda.com",
      "language": "sr",
      "count": 20
    },
    {
      "domain": "serbia.news-pravda.com",
      "language": "sr",
      "count": 41
    },
    {
      "domain": "serbia.news-pravda.com",
      "language": "en",
      "count": 27
    },
    {
      "domain": "ua.news-pravda.com",
      "language": "en",
      "count": 2
    },
    {
      "domain": "ua.news-pravda.com",
      "language": "uk",
      "count": 2
    },
    {
      "domain": "usa.news-pravda.com",
      "language": "en",
      "count": 3
    },
    {
      "domain": "news-pravda.com",
      "language": "en",
      "count": 3
    },
    {
      "domain": "armenia.news-pravda.com",
      "language": "en",
      "count": 1
    },
    {
      "domain": "armenia.news-pravda.com",
      "language": "hy",
      "count": 1
    },
    {
      "domain": "slovakia.news-pravda.com",
      "language": "en",
      "count": 1
    },
    {
      "domain": "slovakia.news-pravda.com",
      "language": "sk",
      "count": 1
    },
    {
      "domain": "albania.news-pravda.com",
      "language": "en",
      "count": 3
    },
    {
      "domain": "albania.news-pravda.com",
      "language": "sq",
      "count": 3
    },
    {
      "domain": "srpska.news-pravda.com",
      "language": "bs",
      "count": 9
    },
    {
      "domain": "srpska.news-pravda.com",
      "language": "sr",
      "count": 19
    },
    {
      "domain": "srpska.news-pravda.com",
      "language": "en",
      "count": 1
    },
    {
      "domain": "eu.news-pravda.com",
      "language": "en",
      "count": 2
    },
    {
      "domain": "bosnia-herzegovina.news-pravda.com",
      "language": "en",
      "count": 7
    },
    {
      "domain": "bosnia-herzegovina.news-pravda.com",
      "language": "bs",
      "count": 8
    },
    {
      "domain": "md.news-pravda.com",
      "language": "ro",
      "count": 1
    },
    {
      "domain": "md.news-pravda.com",
      "language": "en",
      "count": 1
    },
    {
      "domain": "italy.news-pravda.com",
      "language": "en",
      "count": 3
    },
    {
      "domain": "italy.news-pravda.com",
      "language": "it",
      "count": 3
    },
    {
      "domain": "cyprus.news-pravda.com",
      "language": "el",
      "count": 2
    },
    {
      "domain": "cyprus.news-pravda.com",
      "language": "en",
      "count": 2
    },
    {
      "domain": "spanish.news-pravda.com",
      "language": "es",
      "count": 3
    },
    {
      "domain": "germany.news-pravda.com",
      "language": "en",
      "count": 1
    },
    {
      "domain": "germany.news-pravda.com",
      "language": "de",
      "count": 1
    },
    {
      "domain": "deutsch.news-pravda.com",
      "language": "de",
      "count": 2
    },
    {
      "domain": "latvia.news-pravda.com",
      "language": "lv",
      "count": 3
    },
    {
      "domain": "latvia.news-pravda.com",
      "language": "en",
      "count": 3
    },
    {
      "domain": "finland.news-pravda.com",
      "language": "en",
      "count": 3
    },
    {
      "domain": "finland.news-pravda.com",
      "language": "fi",
      "count": 3
    },
    {
      "domain": "egypt.news-pravda.com",
      "language": "en",
      "count": 1
    },
    {
      "domain": "egypt.news-pravda.com",
      "language": "ar",
      "count": 1
    },
    {
      "domain": "turkey.news-pravda.com",
      "language": "tr",
      "count": 1
    },
    {
      "domain": "turkey.news-pravda.com",
      "language": "en",
      "count": 1
    },
    {
      "domain": "france.news-pravda.com",
      "language": "en",
      "count": 1
    },
    {
      "domain": "france.news-pravda.com",
      "language": "fr",
      "count": 1
    },
    {
      "domain": "francais.news-pravda.com",
      "language": "fr",
      "count": 1
    },
    {
      "domain": "dutch.news-pravda.com",
      "language": "nl",
      "count": 1
    },
    {
      "domain": "estonia.news-pravda.com",
      "language": "en",
      "count": 1
    },
    {
      "domain": "estonia.news-pravda.com",
      "language": "et",
      "count": 1
    },
    {
      "domain": "austria.news-pravda.com",
      "language": "en",
      "count": 1
    },
    {
      "domain": "austria.news-pravda.com",
      "language": "de",
      "count": 1
    },
    {
      "domain": "netherlands.news-pravda.com",
      "language": "en",
      "count": 1
    },
    {
      "domain": "netherlands.news-pravda.com",
      "language": "nl",
      "count": 1
    },
    {
      "domain": "lt.news-pravda.com",
      "language": "en",
      "count": 1
    },
    {
      "domain": "lt.news-pravda.com",
      "language": "lt",
      "count": 1
    },
    {
      "domain": "montenegro.news-pravda.com",
      "language": "sr",
      "count": 1
    },
    {
      "domain": "montenegro.news-pravda.com",
      "language": "en",
      "count": 1
    },
    {
      "domain": "croatia.news-pravda.com",
      "language": "hr",
      "count": 1
    },
    {
      "domain": "croatia.news-pravda.com",
      "language": "en",
      "count": 1
    },
    {
      "domain": "uk.news-pravda.com",
      "language": "en",
      "count": 1
    }
  ],
  "countryLanguageData": [
    {
      "code": "sr-RS",
      "count": 41
    },
    {
      "code": "sr",
      "count": 39
    },
    {
      "code": "en",
      "count": 27
    },
    {
      "code": "en-RS",
      "count": 27
    },
    {
      "code": "bs",
      "count": 9
    },
    {
      "code": "bs-BA",
      "count": 8
    },
    {
      "code": "en-BA",
      "count": 7
    },
    {
      "code": "en-US",
      "count": 3
    },
    {
      "code": "en-AL",
      "count": 3
    },
    {
      "code": "sq-AL",
      "count": 3
    },
    {
      "code": "en-IT",
      "count": 3
    },
    {
      "code": "it-IT",
      "count": 3
    },
    {
      "code": "es",
      "count": 3
    },
    {
      "code": "lv-LV",
      "count": 3
    },
    {
      "code": "en-FI",
      "count": 3
    },
    {
      "code": "fi-FI",
      "count": 3
    },
    {
      "code": "en-LV",
      "count": 3
    },
    {
      "code": "en-UA",
      "count": 2
    },
    {
      "code": "uk-UA",
      "count": 2
    },
    {
      "code": "el-CY",
      "count": 2
    },
    {
      "code": "en-CY",
      "count": 2
    },
    {
      "code": "de",
      "count": 2
    },
    {
      "code": "en-AM",
      "count": 1
    },
    {
      "code": "hy-AM",
      "count": 1
    },
    {
      "code": "en-SK",
      "count": 1
    },
    {
      "code": "sk-SK",
      "count": 1
    },
    {
      "code": "ro-MD",
      "count": 1
    },
    {
      "code": "en-MD",
      "count": 1
    },
    {
      "code": "en-DE",
      "count": 1
    },
    {
      "code": "de-DE",
      "count": 1
    },
    {
      "code": "en-EG",
      "count": 1
    },
    {
      "code": "ar-EG",
      "count": 1
    },
    {
      "code": "tr-TR",
      "count": 1
    },
    {
      "code": "en-TR",
      "count": 1
    },
    {
      "code": "en-FR",
      "count": 1
    },
    {
      "code": "fr",
      "count": 1
    },
    {
      "code": "fr-FR",
      "count": 1
    },
    {
      "code": "nl",
      "count": 1
    },
    {
      "code": "en-EE",
      "count": 1
    },
    {
      "code": "en-AT",
      "count": 1
    },
    {
      "code": "en-NL",
      "count": 1
    },
    {
      "code": "et-EE",
      "count": 1
    },
    {
      "code": "de-AT",
      "count": 1
    },
    {
      "code": "en-LT",
      "count": 1
    },
    {
      "code": "nl-NL",
      "count": 1
    },
    {
      "code": "lt-LT",
      "count": 1
    },
    {
      "code": "sr-ME",
      "count": 1
    },
    {
      "code": "en-ME",
      "count": 1
    },
    {
      "code": "hr-HR",
      "count": 1
    },
    {
      "code": "en-HR",
      "count": 1
    },
    {
      "code": "en-GB",
      "count": 1
    }
  ],
  "allDomains": [
    "uk.news-pravda.com",
    "news-pravda.com",
    "balkan.news-pravda.com",
    "turkey.news-pravda.com",
    "albania.news-pravda.com",
    "usa.news-pravda.com",
    "spanish.news-pravda.com",
    "estonia.news-pravda.com",
    "italy.news-pravda.com",
    "serbia.news-pravda.com",
    "latvia.news-pravda.com",
    "srpska.news-pravda.com",
    "md.news-pravda.com",
    "croatia.news-pravda.com",
    "germany.news-pravda.com",
    "francais.news-pravda.com",
    "france.news-pravda.com",
    "lt.news-pravda.com",
    "egypt.news-pravda.com",
    "finland.news-pravda.com",
    "bosnia-herzegovina.news-pravda.com",
    "cyprus.news-pravda.com",
    "armenia.news-pravda.com",
    "eu.news-pravda.com",
    "dutch.news-pravda.com",
    "netherlands.news-pravda.com",
    "deutsch.news-pravda.com",
    "ua.news-pravda.com",
    "austria.news-pravda.com",
    "montenegro.news-pravda.com",
    "slovakia.news-pravda.com"
  ],
  "allLanguages": [
    "nl",
    "uk",
    "el",
    "fr",
    "bs",
    "lt",
    "sq",
    "sk",
    "fi",
    "en",
    "sr",
    "it",
    "de",
    "tr",
    "ar",
    "hr",
    "et",
    "hy",
    "lv",
    "ro",
    "es"
  ]
}