{
  "domain": "syria.news-pravda.com",
  "totalArticles": 2486,
  "articlesPerDay": [
    {
      "date": "2025-06-01",
      "count": 141
    },
    {
      "date": "2025-06-02",
      "count": 351
    },
    {
      "date": "2025-06-03",
      "count": 428
    },
    {
      "date": "2025-06-04",
      "count": 399
    },
    {
      "date": "2025-06-05",
      "count": 425
    },
    {
      "date": "2025-06-06",
      "count": 416
    },
    {
      "date": "2025-06-07",
      "count": 306
    },
    {
      "date": "2025-06-08",
      "count": 20
    }
  ],
  "topSources": [
    {
      "source": "sarabic.ae",
      "count": 562
    },
    {
      "source": "Telegram: Sputnik_Arabic",
      "count": 480
    },
    {
      "source": "Telegram: rtarabicnewsroom",
      "count": 345
    },
    {
      "source": "ar.topwar.ru",
      "count": 334
    },
    {
      "source": "Telegram: tass_ar",
      "count": 172
    },
    {
      "source": "Telegram: RiaArabic",
      "count": 148
    },
    {
      "source": "arabic.rt.com",
      "count": 108
    },
    {
      "source": "Telegram: ukr_leaks_ara",
      "count": 99
    },
    {
      "source": "Telegram: Center_for_Russian_Studies",
      "count": 41
    },
    {
      "source": "Telegram: africaninitiative",
      "count": 40
    },
    {
      "source": "afrinz.ru",
      "count": 38
    },
    {
      "source": "Telegram: InfodefARAB",
      "count": 21
    },
    {
      "source": "ria.ru",
      "count": 11
    },
    {
      "source": "tass.ru",
      "count": 11
    },
    {
      "source": "Telegram: rybar",
      "count": 7
    },
    {
      "source": "Telegram: infantmilitario",
      "count": 6
    },
    {
      "source": "russian.rt.com",
      "count": 5
    },
    {
      "source": "news-front.su",
      "count": 3
    },
    {
      "source": "tsargrad.tv",
      "count": 3
    },
    {
      "source": "Telegram: SolovievLive",
      "count": 3
    },
    {
      "source": "Telegram: Abbasdjuma",
      "count": 3
    },
    {
      "source": "Telegram: rbc_news",
      "count": 3
    },
    {
      "source": "Telegram: olegtsarov",
      "count": 2
    },
    {
      "source": "Telegram: MedvedevVesti",
      "count": 2
    },
    {
      "source": "Telegram: baltnews",
      "count": 2
    },
    {
      "source": "Telegram: hamid_alqawsi",
      "count": 2
    },
    {
      "source": "Telegram: InfodefSpectrum",
      "count": 2
    },
    {
      "source": "lenta.ru",
      "count": 2
    },
    {
      "source": "ren.tv",
      "count": 2
    },
    {
      "source": "Telegram: ukr_2025_ru",
      "count": 2
    },
    {
      "source": "Telegram: SonOfMonarchy",
      "count": 1
    },
    {
      "source": "Telegram: Andrafanaslive",
      "count": 1
    },
    {
      "source": "Telegram: otryadkovpaka",
      "count": 1
    },
    {
      "source": "tvzvezda.ru",
      "count": 1
    },
    {
      "source": "Telegram: vysokygovorit",
      "count": 1
    },
    {
      "source": "Telegram: SYR_313",
      "count": 1
    },
    {
      "source": "crimea.kp.ru",
      "count": 1
    },
    {
      "source": "Telegram: alexandr_malkevich",
      "count": 1
    },
    {
      "source": "crimea24tv.ru",
      "count": 1
    },
    {
      "source": "Telegram: svezhesti",
      "count": 1
    },
    {
      "source": "Telegram: warhistoryalconafter",
      "count": 1
    },
    {
      "source": "Telegram: rt_russian",
      "count": 1
    },
    {
      "source": "Telegram: denazi_UA",
      "count": 1
    },
    {
      "source": "Telegram: voenkorKotenok",
      "count": 1
    },
    {
      "source": "Telegram: a_kuzichev",
      "count": 1
    },
    {
      "source": "kp.ru",
      "count": 1
    },
    {
      "source": "Telegram: opersvodki",
      "count": 1
    },
    {
      "source": "Telegram: tsargradtv",
      "count": 1
    },
    {
      "source": "Telegram: MID_Russia",
      "count": 1
    },
    {
      "source": "Telegram: kommunist",
      "count": 1
    },
    {
      "source": "Telegram: rian_ru",
      "count": 1
    },
    {
      "source": "Telegram: oplottv",
      "count": 1
    },
    {
      "source": "Telegram: kommersant",
      "count": 1
    },
    {
      "source": "Telegram: rentv_news",
      "count": 1
    },
    {
      "source": "Telegram: masaf_najva",
      "count": 1
    },
    {
      "source": "Telegram: Politnavigator",
      "count": 1
    },
    {
      "source": "Telegram: boris_rozhin",
      "count": 1
    }
  ],
  "categories": [
    {
      "category": "syria",
      "count": 1245
    },
    {
      "category": "world",
      "count": 950
    },
    {
      "category": "russia",
      "count": 291
    }
  ],
  "publicationHours": [
    {
      "hour": 0,
      "count": 68
    },
    {
      "hour": 1,
      "count": 78
    },
    {
      "hour": 2,
      "count": 38
    },
    {
      "hour": 3,
      "count": 40
    },
    {
      "hour": 4,
      "count": 26
    },
    {
      "hour": 5,
      "count": 21
    },
    {
      "hour": 6,
      "count": 45
    },
    {
      "hour": 7,
      "count": 54
    },
    {
      "hour": 8,
      "count": 71
    },
    {
      "hour": 9,
      "count": 89
    },
    {
      "hour": 10,
      "count": 129
    },
    {
      "hour": 11,
      "count": 136
    },
    {
      "hour": 12,
      "count": 157
    },
    {
      "hour": 13,
      "count": 158
    },
    {
      "hour": 14,
      "count": 165
    },
    {
      "hour": 15,
      "count": 169
    },
    {
      "hour": 16,
      "count": 165
    },
    {
      "hour": 17,
      "count": 161
    },
    {
      "hour": 18,
      "count": 153
    },
    {
      "hour": 19,
      "count": 130
    },
    {
      "hour": 20,
      "count": 118
    },
    {
      "hour": 21,
      "count": 117
    },
    {
      "hour": 22,
      "count": 94
    },
    {
      "hour": 23,
      "count": 104
    }
  ],
  "sourcesByDay": [
    {
      "date": "2025-06-01",
      "sarabic.ae": 35,
      "Telegram: Sputnik_Arabic": 31,
      "Telegram: rtarabicnewsroom": 21,
      "ar.topwar.ru": 16,
      "Telegram: tass_ar": 10,
      "Telegram: RiaArabic": 6,
      "arabic.rt.com": 4,
      "Telegram: ukr_leaks_ara": 8,
      "Telegram: Center_for_Russian_Studies": 0,
      "Telegram: africaninitiative": 3
    },
    {
      "date": "2025-06-02",
      "sarabic.ae": 92,
      "Telegram: Sputnik_Arabic": 46,
      "Telegram: rtarabicnewsroom": 40,
      "ar.topwar.ru": 57,
      "Telegram: tass_ar": 31,
      "Telegram: RiaArabic": 15,
      "arabic.rt.com": 16,
      "Telegram: ukr_leaks_ara": 10,
      "Telegram: Center_for_Russian_Studies": 7,
      "Telegram: africaninitiative": 4
    },
    {
      "date": "2025-06-03",
      "sarabic.ae": 84,
      "Telegram: Sputnik_Arabic": 70,
      "Telegram: rtarabicnewsroom": 59,
      "ar.topwar.ru": 63,
      "Telegram: tass_ar": 29,
      "Telegram: RiaArabic": 27,
      "arabic.rt.com": 25,
      "Telegram: ukr_leaks_ara": 16,
      "Telegram: Center_for_Russian_Studies": 9,
      "Telegram: africaninitiative": 6
    },
    {
      "date": "2025-06-04",
      "sarabic.ae": 90,
      "Telegram: Sputnik_Arabic": 76,
      "Telegram: rtarabicnewsroom": 54,
      "ar.topwar.ru": 55,
      "Telegram: tass_ar": 11,
      "Telegram: RiaArabic": 44,
      "arabic.rt.com": 27,
      "Telegram: ukr_leaks_ara": 15,
      "Telegram: Center_for_Russian_Studies": 2,
      "Telegram: africaninitiative": 2
    },
    {
      "date": "2025-06-05",
      "sarabic.ae": 98,
      "Telegram: Sputnik_Arabic": 87,
      "Telegram: rtarabicnewsroom": 54,
      "ar.topwar.ru": 53,
      "Telegram: tass_ar": 40,
      "Telegram: RiaArabic": 24,
      "arabic.rt.com": 12,
      "Telegram: ukr_leaks_ara": 17,
      "Telegram: Center_for_Russian_Studies": 6,
      "Telegram: africaninitiative": 9
    },
    {
      "date": "2025-06-06",
      "sarabic.ae": 86,
      "Telegram: Sputnik_Arabic": 86,
      "Telegram: rtarabicnewsroom": 65,
      "ar.topwar.ru": 57,
      "Telegram: tass_ar": 35,
      "Telegram: RiaArabic": 23,
      "arabic.rt.com": 13,
      "Telegram: ukr_leaks_ara": 15,
      "Telegram: Center_for_Russian_Studies": 10,
      "Telegram: africaninitiative": 9
    },
    {
      "date": "2025-06-07",
      "sarabic.ae": 75,
      "Telegram: Sputnik_Arabic": 78,
      "Telegram: rtarabicnewsroom": 45,
      "ar.topwar.ru": 33,
      "Telegram: tass_ar": 15,
      "Telegram: RiaArabic": 9,
      "arabic.rt.com": 10,
      "Telegram: ukr_leaks_ara": 16,
      "Telegram: Center_for_Russian_Studies": 6,
      "Telegram: africaninitiative": 7
    },
    {
      "date": "2025-06-08",
      "sarabic.ae": 2,
      "Telegram: Sputnik_Arabic": 6,
      "Telegram: rtarabicnewsroom": 7,
      "ar.topwar.ru": 0,
      "Telegram: tass_ar": 1,
      "Telegram: RiaArabic": 0,
      "arabic.rt.com": 1,
      "Telegram: ukr_leaks_ara": 2,
      "Telegram: Center_for_Russian_Studies": 1,
      "Telegram: africaninitiative": 0
    }
  ],
  "topSourceNames": [
    "sarabic.ae",
    "Telegram: Sputnik_Arabic",
    "Telegram: rtarabicnewsroom",
    "ar.topwar.ru",
    "Telegram: tass_ar",
    "Telegram: RiaArabic",
    "arabic.rt.com",
    "Telegram: ukr_leaks_ara",
    "Telegram: Center_for_Russian_Studies",
    "Telegram: africaninitiative"
  ],
  "alternatesStats": {
    "articlesWithAlternates": 2486,
    "percentWithAlternates": 100.0,
    "avgAlternatesPerArticle": 1.8153660498793243
  },
  "languages": [
    {
      "language": "ar",
      "count": 1566
    },
    {
      "language": "en",
      "count": 332
    },
    {
      "language": "fr",
      "count": 50
    },
    {
      "language": "tr",
      "count": 38
    },
    {
      "language": "de",
      "count": 12
    },
    {
      "language": "it",
      "count": 4
    },
    {
      "language": "sv",
      "count": 4
    },
    {
      "language": "es",
      "count": 2
    },
    {
      "language": "el",
      "count": 2
    },
    {
      "language": "fi",
      "count": 2
    },
    {
      "language": "hr",
      "count": 2
    },
    {
      "language": "no",
      "count": 2
    },
    {
      "language": "et",
      "count": 2
    },
    {
      "language": "ja",
      "count": 2
    },
    {
      "language": "da",
      "count": 2
    },
    {
      "language": "ka",
      "count": 2
    },
    {
      "language": "ca",
      "count": 1
    },
    {
      "language": "sr",
      "count": 1
    }
  ],
  "languageConnections": [
    {
      "source": "en",
      "target": "ar",
      "strength": 117
    },
    {
      "source": "en",
      "target": "fr",
      "strength": 22
    },
    {
      "source": "en",
      "target": "tr",
      "strength": 19
    },
    {
      "source": "en",
      "target": "de",
      "strength": 7
    },
    {
      "source": "en",
      "target": "it",
      "strength": 2
    },
    {
      "source": "en",
      "target": "sv",
      "strength": 2
    },
    {
      "source": "en",
      "target": "ca",
      "strength": 1
    },
    {
      "source": "en",
      "target": "es",
      "strength": 1
    },
    {
      "source": "en",
      "target": "el",
      "strength": 1
    },
    {
      "source": "en",
      "target": "hr",
      "strength": 1
    },
    {
      "source": "en",
      "target": "no",
      "strength": 1
    },
    {
      "source": "en",
      "target": "fi",
      "strength": 1
    },
    {
      "source": "en",
      "target": "sr",
      "strength": 1
    },
    {
      "source": "en",
      "target": "et",
      "strength": 1
    },
    {
      "source": "en",
      "target": "ja",
      "strength": 1
    },
    {
      "source": "en",
      "target": "da",
      "strength": 1
    },
    {
      "source": "en",
      "target": "ka",
      "strength": 1
    },
    {
      "source": "ar",
      "target": "en",
      "strength": 117
    },
    {
      "source": "ar",
      "target": "fr",
      "strength": 22
    },
    {
      "source": "ar",
      "target": "tr",
      "strength": 19
    },
    {
      "source": "ar",
      "target": "de",
      "strength": 7
    },
    {
      "source": "ar",
      "target": "it",
      "strength": 2
    },
    {
      "source": "ar",
      "target": "sv",
      "strength": 2
    },
    {
      "source": "ar",
      "target": "ca",
      "strength": 1
    },
    {
      "source": "ar",
      "target": "es",
      "strength": 1
    },
    {
      "source": "ar",
      "target": "el",
      "strength": 1
    },
    {
      "source": "ar",
      "target": "hr",
      "strength": 1
    },
    {
      "source": "ar",
      "target": "no",
      "strength": 1
    },
    {
      "source": "ar",
      "target": "fi",
      "strength": 1
    },
    {
      "source": "ar",
      "target": "sr",
      "strength": 1
    },
    {
      "source": "ar",
      "target": "et",
      "strength": 1
    },
    {
      "source": "ar",
      "target": "ja",
      "strength": 1
    },
    {
      "source": "ar",
      "target": "da",
      "strength": 1
    },
    {
      "source": "ar",
      "target": "ka",
      "strength": 1
    },
    {
      "source": "tr",
      "target": "en",
      "strength": 19
    },
    {
      "source": "tr",
      "target": "ar",
      "strength": 19
    },
    {
      "source": "tr",
      "target": "fr",
      "strength": 3
    },
    {
      "source": "tr",
      "target": "de",
      "strength": 3
    },
    {
      "source": "tr",
      "target": "el",
      "strength": 1
    },
    {
      "source": "tr",
      "target": "hr",
      "strength": 1
    },
    {
      "source": "tr",
      "target": "no",
      "strength": 1
    },
    {
      "source": "tr",
      "target": "it",
      "strength": 1
    },
    {
      "source": "tr",
      "target": "fi",
      "strength": 1
    },
    {
      "source": "tr",
      "target": "sr",
      "strength": 1
    },
    {
      "source": "tr",
      "target": "sv",
      "strength": 1
    },
    {
      "source": "fr",
      "target": "en",
      "strength": 22
    },
    {
      "source": "fr",
      "target": "ar",
      "strength": 22
    },
    {
      "source": "fr",
      "target": "de",
      "strength": 5
    },
    {
      "source": "fr",
      "target": "tr",
      "strength": 3
    },
    {
      "source": "fr",
      "target": "hr",
      "strength": 1
    },
    {
      "source": "fr",
      "target": "no",
      "strength": 1
    },
    {
      "source": "fr",
      "target": "it",
      "strength": 1
    },
    {
      "source": "fr",
      "target": "fi",
      "strength": 1
    },
    {
      "source": "fr",
      "target": "sr",
      "strength": 1
    },
    {
      "source": "fr",
      "target": "sv",
      "strength": 1
    },
    {
      "source": "fr",
      "target": "ka",
      "strength": 1
    },
    {
      "source": "ca",
      "target": "en",
      "strength": 1
    },
    {
      "source": "ca",
      "target": "es",
      "strength": 1
    },
    {
      "source": "ca",
      "target": "ar",
      "strength": 1
    },
    {
      "source": "es",
      "target": "en",
      "strength": 1
    },
    {
      "source": "es",
      "target": "ca",
      "strength": 1
    },
    {
      "source": "es",
      "target": "ar",
      "strength": 1
    },
    {
      "source": "de",
      "target": "en",
      "strength": 7
    },
    {
      "source": "de",
      "target": "ar",
      "strength": 7
    },
    {
      "source": "de",
      "target": "fr",
      "strength": 5
    },
    {
      "source": "de",
      "target": "tr",
      "strength": 3
    },
    {
      "source": "de",
      "target": "hr",
      "strength": 1
    },
    {
      "source": "de",
      "target": "no",
      "strength": 1
    },
    {
      "source": "de",
      "target": "it",
      "strength": 1
    },
    {
      "source": "de",
      "target": "fi",
      "strength": 1
    },
    {
      "source": "de",
      "target": "sr",
      "strength": 1
    },
    {
      "source": "de",
      "target": "sv",
      "strength": 1
    },
    {
      "source": "el",
      "target": "en",
      "strength": 1
    },
    {
      "source": "el",
      "target": "tr",
      "strength": 1
    },
    {
      "source": "el",
      "target": "ar",
      "strength": 1
    },
    {
      "source": "hr",
      "target": "fr",
      "strength": 1
    },
    {
      "source": "hr",
      "target": "tr",
      "strength": 1
    },
    {
      "source": "hr",
      "target": "no",
      "strength": 1
    },
    {
      "source": "hr",
      "target": "it",
      "strength": 1
    },
    {
      "source": "hr",
      "target": "en",
      "strength": 1
    },
    {
      "source": "hr",
      "target": "fi",
      "strength": 1
    },
    {
      "source": "hr",
      "target": "sr",
      "strength": 1
    },
    {
      "source": "hr",
      "target": "ar",
      "strength": 1
    },
    {
      "source": "hr",
      "target": "de",
      "strength": 1
    },
    {
      "source": "no",
      "target": "hr",
      "strength": 1
    },
    {
      "source": "no",
      "target": "fr",
      "strength": 1
    },
    {
      "source": "no",
      "target": "tr",
      "strength": 1
    },
    {
      "source": "no",
      "target": "it",
      "strength": 1
    },
    {
      "source": "no",
      "target": "en",
      "strength": 1
    },
    {
      "source": "no",
      "target": "fi",
      "strength": 1
    },
    {
      "source": "no",
      "target": "sr",
      "strength": 1
    },
    {
      "source": "no",
      "target": "ar",
      "strength": 1
    },
    {
      "source": "no",
      "target": "de",
      "strength": 1
    },
    {
      "source": "it",
      "target": "en",
      "strength": 2
    },
    {
      "source": "it",
      "target": "ar",
      "strength": 2
    },
    {
      "source": "it",
      "target": "hr",
      "strength": 1
    },
    {
      "source": "it",
      "target": "fr",
      "strength": 1
    },
    {
      "source": "it",
      "target": "tr",
      "strength": 1
    },
    {
      "source": "it",
      "target": "no",
      "strength": 1
    },
    {
      "source": "it",
      "target": "fi",
      "strength": 1
    },
    {
      "source": "it",
      "target": "sr",
      "strength": 1
    },
    {
      "source": "it",
      "target": "de",
      "strength": 1
    },
    {
      "source": "fi",
      "target": "hr",
      "strength": 1
    },
    {
      "source": "fi",
      "target": "fr",
      "strength": 1
    },
    {
      "source": "fi",
      "target": "tr",
      "strength": 1
    },
    {
      "source": "fi",
      "target": "no",
      "strength": 1
    },
    {
      "source": "fi",
      "target": "it",
      "strength": 1
    },
    {
      "source": "fi",
      "target": "en",
      "strength": 1
    },
    {
      "source": "fi",
      "target": "sr",
      "strength": 1
    },
    {
      "source": "fi",
      "target": "ar",
      "strength": 1
    },
    {
      "source": "fi",
      "target": "de",
      "strength": 1
    },
    {
      "source": "sr",
      "target": "hr",
      "strength": 1
    },
    {
      "source": "sr",
      "target": "fr",
      "strength": 1
    },
    {
      "source": "sr",
      "target": "tr",
      "strength": 1
    },
    {
      "source": "sr",
      "target": "no",
      "strength": 1
    },
    {
      "source": "sr",
      "target": "it",
      "strength": 1
    },
    {
      "source": "sr",
      "target": "en",
      "strength": 1
    },
    {
      "source": "sr",
      "target": "fi",
      "strength": 1
    },
    {
      "source": "sr",
      "target": "ar",
      "strength": 1
    },
    {
      "source": "sr",
      "target": "de",
      "strength": 1
    },
    {
      "source": "et",
      "target": "en",
      "strength": 1
    },
    {
      "source": "et",
      "target": "sv",
      "strength": 1
    },
    {
      "source": "et",
      "target": "ar",
      "strength": 1
    },
    {
      "source": "sv",
      "target": "en",
      "strength": 2
    },
    {
      "source": "sv",
      "target": "ar",
      "strength": 2
    },
    {
      "source": "sv",
      "target": "et",
      "strength": 1
    },
    {
      "source": "sv",
      "target": "fr",
      "strength": 1
    },
    {
      "source": "sv",
      "target": "tr",
      "strength": 1
    },
    {
      "source": "sv",
      "target": "de",
      "strength": 1
    },
    {
      "source": "ja",
      "target": "en",
      "strength": 1
    },
    {
      "source": "ja",
      "target": "ar",
      "strength": 1
    },
    {
      "source": "da",
      "target": "en",
      "strength": 1
    },
    {
      "source": "da",
      "target": "ar",
      "strength": 1
    },
    {
      "source": "ka",
      "target": "fr",
      "strength": 1
    },
    {
      "source": "ka",
      "target": "en",
      "strength": 1
    },
    {
      "source": "ka",
      "target": "ar",
      "strength": 1
    }
  ],
  "domainLanguageData": [
    {
      "domain": "sudan.news-pravda.com",
      "language": "ar",
      "count": 186
    },
    {
      "domain": "sudan.news-pravda.com",
      "language": "en",
      "count": 10
    },
    {
      "domain": "syria.news-pravda.com",
      "language": "ar",
      "count": 878
    },
    {
      "domain": "syria.news-pravda.com",
      "language": "en",
      "count": 131
    },
    {
      "domain": "chad.news-pravda.com",
      "language": "ar",
      "count": 119
    },
    {
      "domain": "chad.news-pravda.com",
      "language": "en",
      "count": 3
    },
    {
      "domain": "chad.news-pravda.com",
      "language": "fr",
      "count": 5
    },
    {
      "domain": "egypt.news-pravda.com",
      "language": "ar",
      "count": 304
    },
    {
      "domain": "egypt.news-pravda.com",
      "language": "en",
      "count": 2
    },
    {
      "domain": "turkey.news-pravda.com",
      "language": "en",
      "count": 24
    },
    {
      "domain": "turkey.news-pravda.com",
      "language": "tr",
      "count": 38
    },
    {
      "domain": "news-pravda.com",
      "language": "en",
      "count": 33
    },
    {
      "domain": "niger.news-pravda.com",
      "language": "fr",
      "count": 9
    },
    {
      "domain": "niger.news-pravda.com",
      "language": "en",
      "count": 10
    },
    {
      "domain": "usa.news-pravda.com",
      "language": "en",
      "count": 36
    },
    {
      "domain": "trump.news-pravda.com",
      "language": "en",
      "count": 8
    },
    {
      "domain": "algeria.news-pravda.com",
      "language": "ar",
      "count": 55
    },
    {
      "domain": "mauritania.news-pravda.com",
      "language": "ar",
      "count": 19
    },
    {
      "domain": "mauritania.news-pravda.com",
      "language": "en",
      "count": 1
    },
    {
      "domain": "nigeria.news-pravda.com",
      "language": "en",
      "count": 7
    },
    {
      "domain": "spain.news-pravda.com",
      "language": "en",
      "count": 2
    },
    {
      "domain": "spain.news-pravda.com",
      "language": "es",
      "count": 1
    },
    {
      "domain": "spanish.news-pravda.com",
      "language": "es",
      "count": 1
    },
    {
      "domain": "catalan.news-pravda.com",
      "language": "ca",
      "count": 1
    },
    {
      "domain": "deutsch.news-pravda.com",
      "language": "de",
      "count": 7
    },
    {
      "domain": "abkhazia.news-pravda.com",
      "language": "en",
      "count": 1
    },
    {
      "domain": "canada.news-pravda.com",
      "language": "en",
      "count": 3
    },
    {
      "domain": "canada.news-pravda.com",
      "language": "fr",
      "count": 4
    },
    {
      "domain": "france.news-pravda.com",
      "language": "en",
      "count": 6
    },
    {
      "domain": "france.news-pravda.com",
      "language": "fr",
      "count": 3
    },
    {
      "domain": "francais.news-pravda.com",
      "language": "fr",
      "count": 5
    },
    {
      "domain": "burkina-faso.news-pravda.com",
      "language": "en",
      "count": 8
    },
    {
      "domain": "burkina-faso.news-pravda.com",
      "language": "fr",
      "count": 8
    },
    {
      "domain": "mali.news-pravda.com",
      "language": "fr",
      "count": 6
    },
    {
      "domain": "mali.news-pravda.com",
      "language": "en",
      "count": 7
    },
    {
      "domain": "cameroon.news-pravda.com",
      "language": "en",
      "count": 2
    },
    {
      "domain": "greece.news-pravda.com",
      "language": "el",
      "count": 2
    },
    {
      "domain": "greece.news-pravda.com",
      "language": "en",
      "count": 1
    },
    {
      "domain": "senegal.news-pravda.com",
      "language": "fr",
      "count": 2
    },
    {
      "domain": "senegal.news-pravda.com",
      "language": "en",
      "count": 1
    },
    {
      "domain": "guinea.news-pravda.com",
      "language": "en",
      "count": 5
    },
    {
      "domain": "guinea.news-pravda.com",
      "language": "fr",
      "count": 6
    },
    {
      "domain": "eritrea.news-pravda.com",
      "language": "en",
      "count": 1
    },
    {
      "domain": "eritrea.news-pravda.com",
      "language": "ar",
      "count": 5
    },
    {
      "domain": "finland.news-pravda.com",
      "language": "fi",
      "count": 2
    },
    {
      "domain": "finland.news-pravda.com",
      "language": "en",
      "count": 1
    },
    {
      "domain": "croatia.news-pravda.com",
      "language": "hr",
      "count": 2
    },
    {
      "domain": "croatia.news-pravda.com",
      "language": "en",
      "count": 1
    },
    {
      "domain": "norway.news-pravda.com",
      "language": "no",
      "count": 2
    },
    {
      "domain": "norway.news-pravda.com",
      "language": "en",
      "count": 1
    },
    {
      "domain": "italy.news-pravda.com",
      "language": "en",
      "count": 2
    },
    {
      "domain": "italy.news-pravda.com",
      "language": "it",
      "count": 4
    },
    {
      "domain": "au.news-pravda.com",
      "language": "en",
      "count": 1
    },
    {
      "domain": "balkan.news-pravda.com",
      "language": "en",
      "count": 1
    },
    {
      "domain": "balkan.news-pravda.com",
      "language": "sr",
      "count": 1
    },
    {
      "domain": "uk.news-pravda.com",
      "language": "en",
      "count": 3
    },
    {
      "domain": "poland.news-pravda.com",
      "language": "en",
      "count": 1
    },
    {
      "domain": "estonia.news-pravda.com",
      "language": "et",
      "count": 2
    },
    {
      "domain": "estonia.news-pravda.com",
      "language": "en",
      "count": 1
    },
    {
      "domain": "eu.news-pravda.com",
      "language": "en",
      "count": 4
    },
    {
      "domain": "sweden.news-pravda.com",
      "language": "sv",
      "count": 4
    },
    {
      "domain": "sweden.news-pravda.com",
      "language": "en",
      "count": 2
    },
    {
      "domain": "japan.news-pravda.com",
      "language": "ja",
      "count": 2
    },
    {
      "domain": "japan.news-pravda.com",
      "language": "en",
      "count": 2
    },
    {
      "domain": "germany.news-pravda.com",
      "language": "en",
      "count": 2
    },
    {
      "domain": "germany.news-pravda.com",
      "language": "de",
      "count": 2
    },
    {
      "domain": "switzerland.news-pravda.com",
      "language": "en",
      "count": 2
    },
    {
      "domain": "switzerland.news-pravda.com",
      "language": "fr",
      "count": 2
    },
    {
      "domain": "switzerland.news-pravda.com",
      "language": "de",
      "count": 2
    },
    {
      "domain": "austria.news-pravda.com",
      "language": "en",
      "count": 2
    },
    {
      "domain": "austria.news-pravda.com",
      "language": "de",
      "count": 1
    },
    {
      "domain": "denmark.news-pravda.com",
      "language": "en",
      "count": 2
    },
    {
      "domain": "denmark.news-pravda.com",
      "language": "da",
      "count": 2
    },
    {
      "domain": "nato.news-pravda.com",
      "language": "en",
      "count": 1
    },
    {
      "domain": "ge.news-pravda.com",
      "language": "ka",
      "count": 2
    },
    {
      "domain": "ge.news-pravda.com",
      "language": "en",
      "count": 1
    }
  ],
  "countryLanguageData": [
    {
      "code": "ar-SY",
      "count": 538
    },
    {
      "code": "ar",
      "count": 538
    },
    {
      "code": "ar-EG",
      "count": 217
    },
    {
      "code": "ar-SD",
      "count": 133
    },
    {
      "code": "en",
      "count": 117
    },
    {
      "code": "en-SY",
      "count": 88
    },
    {
      "code": "ar-TD",
      "count": 82
    },
    {
      "code": "ar-DZ",
      "count": 42
    },
    {
      "code": "en-US",
      "count": 34
    },
    {
      "code": "fr",
      "count": 22
    },
    {
      "code": "en-TR",
      "count": 20
    },
    {
      "code": "tr-TR",
      "count": 19
    },
    {
      "code": "tr",
      "count": 19
    },
    {
      "code": "ar-MR",
      "count": 13
    },
    {
      "code": "en-SD",
      "count": 7
    },
    {
      "code": "de",
      "count": 7
    },
    {
      "code": "fr-NE",
      "count": 6
    },
    {
      "code": "en-NE",
      "count": 6
    },
    {
      "code": "en-FR",
      "count": 6
    },
    {
      "code": "en-BF",
      "count": 6
    },
    {
      "code": "en-NG",
      "count": 5
    },
    {
      "code": "en-ML",
      "count": 5
    },
    {
      "code": "fr-BF",
      "count": 5
    },
    {
      "code": "fr-ML",
      "count": 4
    },
    {
      "code": "en-TD",
      "count": 3
    },
    {
      "code": "fr-TD",
      "count": 3
    },
    {
      "code": "en-GN",
      "count": 3
    },
    {
      "code": "fr-GN",
      "count": 3
    },
    {
      "code": "ar-ER",
      "count": 3
    },
    {
      "code": "en-GB",
      "count": 3
    },
    {
      "code": "fr-FR",
      "count": 3
    },
    {
      "code": "en-CA",
      "count": 2
    },
    {
      "code": "en-IT",
      "count": 2
    },
    {
      "code": "it-IT",
      "count": 2
    },
    {
      "code": "it",
      "count": 2
    },
    {
      "code": "en-EG",
      "count": 2
    },
    {
      "code": "sv-SE",
      "count": 2
    },
    {
      "code": "en-SE",
      "count": 2
    },
    {
      "code": "sv",
      "count": 2
    },
    {
      "code": "fr-CA",
      "count": 2
    },
    {
      "code": "en-DE",
      "count": 2
    },
    {
      "code": "de-DE",
      "count": 2
    },
    {
      "code": "en-CH",
      "count": 2
    },
    {
      "code": "en-AT",
      "count": 2
    },
    {
      "code": "de-CH",
      "count": 2
    },
    {
      "code": "en-ES",
      "count": 1
    },
    {
      "code": "es",
      "count": 1
    },
    {
      "code": "es-ES",
      "count": 1
    },
    {
      "code": "ca",
      "count": 1
    },
    {
      "code": "en-CM",
      "count": 1
    },
    {
      "code": "el-GR",
      "count": 1
    },
    {
      "code": "en-GR",
      "count": 1
    },
    {
      "code": "el",
      "count": 1
    },
    {
      "code": "fr-SN",
      "count": 1
    },
    {
      "code": "en-SN",
      "count": 1
    },
    {
      "code": "en-MR",
      "count": 1
    },
    {
      "code": "en-ER",
      "count": 1
    },
    {
      "code": "fi-FI",
      "count": 1
    },
    {
      "code": "hr-HR",
      "count": 1
    },
    {
      "code": "no-NO",
      "count": 1
    },
    {
      "code": "en-NO",
      "count": 1
    },
    {
      "code": "en-AU",
      "count": 1
    },
    {
      "code": "en-FI",
      "count": 1
    },
    {
      "code": "en-HR",
      "count": 1
    },
    {
      "code": "fi",
      "count": 1
    },
    {
      "code": "hr",
      "count": 1
    },
    {
      "code": "no",
      "count": 1
    },
    {
      "code": "sr",
      "count": 1
    },
    {
      "code": "en-PL",
      "count": 1
    },
    {
      "code": "et-EE",
      "count": 1
    },
    {
      "code": "en-EE",
      "count": 1
    },
    {
      "code": "et",
      "count": 1
    },
    {
      "code": "ja-JP",
      "count": 1
    },
    {
      "code": "en-JP",
      "count": 1
    },
    {
      "code": "ja",
      "count": 1
    },
    {
      "code": "fr-CH",
      "count": 1
    },
    {
      "code": "de-AT",
      "count": 1
    },
    {
      "code": "en-DK",
      "count": 1
    },
    {
      "code": "da-DK",
      "count": 1
    },
    {
      "code": "da",
      "count": 1
    },
    {
      "code": "ka-GE",
      "count": 1
    },
    {
      "code": "en-GE",
      "count": 1
    },
    {
      "code": "ka",
      "count": 1
    }
  ],
  "allDomains": [
    "denmark.news-pravda.com",
    "trump.news-pravda.com",
    "catalan.news-pravda.com",
    "senegal.news-pravda.com",
    "eritrea.news-pravda.com",
    "greece.news-pravda.com",
    "sudan.news-pravda.com",
    "syria.news-pravda.com",
    "germany.news-pravda.com",
    "eu.news-pravda.com",
    "estonia.news-pravda.com",
    "niger.news-pravda.com",
    "spain.news-pravda.com",
    "ge.news-pravda.com",
    "nato.news-pravda.com",
    "croatia.news-pravda.com",
    "usa.news-pravda.com",
    "algeria.news-pravda.com",
    "chad.news-pravda.com",
    "finland.news-pravda.com",
    "abkhazia.news-pravda.com",
    "balkan.news-pravda.com",
    "canada.news-pravda.com",
    "switzerland.news-pravda.com",
    "burkina-faso.news-pravda.com",
    "cameroon.news-pravda.com",
    "mauritania.news-pravda.com",
    "poland.news-pravda.com",
    "france.news-pravda.com",
    "egypt.news-pravda.com",
    "guinea.news-pravda.com",
    "spanish.news-pravda.com",
    "francais.news-pravda.com",
    "mali.news-pravda.com",
    "norway.news-pravda.com",
    "news-pravda.com",
    "au.news-pravda.com",
    "uk.news-pravda.com",
    "austria.news-pravda.com",
    "turkey.news-pravda.com",
    "italy.news-pravda.com",
    "japan.news-pravda.com",
    "sweden.news-pravda.com",
    "deutsch.news-pravda.com",
    "nigeria.news-pravda.com"
  ],
  "allLanguages": [
    "ja",
    "hr",
    "da",
    "es",
    "ka",
    "fr",
    "et",
    "tr",
    "no",
    "it",
    "sv",
    "en",
    "el",
    "fi",
    "sr",
    "de",
    "ca",
    "ar"
  ]
}