{
  "domain": "trump.news-pravda.com",
  "totalArticles": 1282,
  "articlesPerDay": [
    {
      "date": "2025-06-06",
      "count": 307
    },
    {
      "date": "2025-06-07",
      "count": 337
    },
    {
      "date": "2025-06-09",
      "count": 245
    },
    {
      "date": "2025-06-10",
      "count": 137
    },
    {
      "date": "2025-06-11",
      "count": 256
    }
  ],
  "topSources": [
    {
      "source": "lenta.ru",
      "count": 60
    },
    {
      "source": "kp.ru",
      "count": 50
    },
    {
      "source": "tass.ru",
      "count": 47
    },
    {
      "source": "ria.ru",
      "count": 46
    },
    {
      "source": "russian.rt.com",
      "count": 44
    },
    {
      "source": "Telegram: lomovkaa",
      "count": 43
    },
    {
      "source": "tsargrad.tv",
      "count": 37
    },
    {
      "source": "Telegram: SolovievLive",
      "count": 33
    },
    {
      "source": "ren.tv",
      "count": 31
    },
    {
      "source": "Telegram: rtnews",
      "count": 31
    },
    {
      "source": "Telegram: SGTnewsNetwork",
      "count": 27
    },
    {
      "source": "swentr.site",
      "count": 25
    },
    {
      "source": "Telegram: ruptlyalert",
      "count": 22
    },
    {
      "source": "en.topwar.ru",
      "count": 22
    },
    {
      "source": "Telegram: izvestia",
      "count": 21
    },
    {
      "source": "Telegram: MaksLifeOff",
      "count": 21
    },
    {
      "source": "Telegram: geopolitics_live",
      "count": 20
    },
    {
      "source": "Telegram: tassagency_en",
      "count": 19
    },
    {
      "source": "en.news-front.su",
      "count": 17
    },
    {
      "source": "Telegram: TheIslanderNews",
      "count": 16
    },
    {
      "source": "news-front.su",
      "count": 16
    },
    {
      "source": "tass.com",
      "count": 15
    },
    {
      "source": "Telegram: rt_russian",
      "count": 14
    },
    {
      "source": "Telegram: tass_world",
      "count": 14
    },
    {
      "source": "Telegram: tsargradtv",
      "count": 14
    },
    {
      "source": "Telegram: DDGeopolitics",
      "count": 13
    },
    {
      "source": "Telegram: myLordBebo",
      "count": 13
    },
    {
      "source": "sputnikglobe.com",
      "count": 13
    },
    {
      "source": "Telegram: dimsmirnov175",
      "count": 13
    },
    {
      "source": "tvzvezda.ru",
      "count": 12
    },
    {
      "source": "Telegram: rianovostiAmerica",
      "count": 12
    },
    {
      "source": "Telegram: rian_ru",
      "count": 12
    },
    {
      "source": "Telegram: llordofwar",
      "count": 11
    },
    {
      "source": "Telegram: Politnavigator",
      "count": 11
    },
    {
      "source": "Telegram: europeandusanews",
      "count": 11
    },
    {
      "source": "Telegram: ukr_2025_ru",
      "count": 10
    },
    {
      "source": "Telegram: ntvnews",
      "count": 10
    },
    {
      "source": "radiosputnik.ru",
      "count": 10
    },
    {
      "source": "Telegram: kommersant",
      "count": 10
    },
    {
      "source": "Telegram: vestiru24",
      "count": 9
    },
    {
      "source": "Telegram: ostashkonews",
      "count": 9
    },
    {
      "source": "Telegram: ukraine_watch",
      "count": 9
    },
    {
      "source": "Telegram: i20028843",
      "count": 9
    },
    {
      "source": "Telegram: malekdudakov",
      "count": 9
    },
    {
      "source": "Telegram: radio_sputnik",
      "count": 9
    },
    {
      "source": "Telegram: olegtsarov",
      "count": 8
    },
    {
      "source": "Telegram: infantmilitario",
      "count": 8
    },
    {
      "source": "Telegram: rbc_news",
      "count": 8
    },
    {
      "source": "Telegram: Slavyangrad",
      "count": 7
    },
    {
      "source": "Telegram: bioclandestine",
      "count": 7
    },
    {
      "source": "Telegram: cgtn_europe",
      "count": 7
    },
    {
      "source": "Telegram: EvPanina",
      "count": 7
    },
    {
      "source": "Telegram: GardeZ66",
      "count": 7
    },
    {
      "source": "Telegram: InfodefSpectrum",
      "count": 7
    },
    {
      "source": "Telegram: SputnikInt",
      "count": 7
    },
    {
      "source": "Telegram: news_1tv",
      "count": 7
    },
    {
      "source": "Telegram: AussieCossack",
      "count": 7
    },
    {
      "source": "Telegram: logikamarkova",
      "count": 6
    },
    {
      "source": "Telegram: mardanaka",
      "count": 6
    },
    {
      "source": "Telegram: inosmichannel",
      "count": 6
    },
    {
      "source": "Telegram: politjoystic",
      "count": 6
    },
    {
      "source": "ukraina.ru",
      "count": 6
    },
    {
      "source": "Telegram: rybar",
      "count": 6
    },
    {
      "source": "Telegram: bbbreaking",
      "count": 5
    },
    {
      "source": "Telegram: sputniklive",
      "count": 5
    },
    {
      "source": "Telegram: node_of_time_en",
      "count": 5
    },
    {
      "source": "Telegram: kornilov1968",
      "count": 5
    },
    {
      "source": "Telegram: sputnik_africa",
      "count": 5
    },
    {
      "source": "Telegram: intnewsagency",
      "count": 5
    },
    {
      "source": "Telegram: baltnews",
      "count": 5
    },
    {
      "source": "Telegram: zhivoff",
      "count": 5
    },
    {
      "source": "Telegram: uranews",
      "count": 4
    },
    {
      "source": "Telegram: two_majors",
      "count": 4
    },
    {
      "source": "Telegram: NasonovLive",
      "count": 4
    },
    {
      "source": "baltnews.com",
      "count": 4
    },
    {
      "source": "en.sputniknews.africa",
      "count": 4
    },
    {
      "source": "Telegram: vicktop55",
      "count": 4
    },
    {
      "source": "Telegram: AbzalovD",
      "count": 4
    },
    {
      "source": "Telegram: btr80_en",
      "count": 3
    },
    {
      "source": "Telegram: GrafinyaNegoduet",
      "count": 3
    },
    {
      "source": "Telegram: TASS_europe",
      "count": 3
    },
    {
      "source": "Telegram: goingundergroundRT",
      "count": 3
    },
    {
      "source": "Telegram: newsfrontnotes",
      "count": 3
    },
    {
      "source": "Telegram: a_kuzichev",
      "count": 3
    },
    {
      "source": "Telegram: zvezda_analytics",
      "count": 3
    },
    {
      "source": "Telegram: nstarikovru",
      "count": 3
    },
    {
      "source": "Telegram: SMIcrimea",
      "count": 3
    },
    {
      "source": "Telegram: rentv_news",
      "count": 3
    },
    {
      "source": "Telegram: ukr_leaks_eng",
      "count": 3
    },
    {
      "source": "Telegram: warhistoryalconafter",
      "count": 3
    },
    {
      "source": "Telegram: fr0m_Russia_with_L0ve",
      "count": 3
    },
    {
      "source": "Telegram: DDrobnitski",
      "count": 3
    },
    {
      "source": "Telegram: denazi_UA",
      "count": 3
    },
    {
      "source": "Telegram: new_militarycolumnist",
      "count": 3
    },
    {
      "source": "Telegram: tass_agency",
      "count": 3
    },
    {
      "source": "Telegram: dr_alex_sosnowski",
      "count": 2
    },
    {
      "source": "Telegram: Mikle1On",
      "count": 2
    },
    {
      "source": "Telegram: WarDonbass",
      "count": 2
    },
    {
      "source": "Telegram: sardaryanh",
      "count": 2
    },
    {
      "source": "Telegram: barantchik",
      "count": 2
    },
    {
      "source": "Telegram: boris_rozhin",
      "count": 2
    },
    {
      "source": "Telegram: vityzeva",
      "count": 2
    },
    {
      "source": "Telegram: otryadkovpaka",
      "count": 2
    },
    {
      "source": "Telegram: maximgrigoryev",
      "count": 2
    },
    {
      "source": "Telegram: MilThemeZ",
      "count": 2
    },
    {
      "source": "Telegram: pdmnews",
      "count": 2
    },
    {
      "source": "Telegram: oplotdvizh",
      "count": 2
    },
    {
      "source": "Telegram: btr80",
      "count": 2
    },
    {
      "source": "Telegram: CyberspecNews",
      "count": 2
    },
    {
      "source": "Telegram: Alekhin_Telega",
      "count": 2
    },
    {
      "source": "Telegram: valentinbogdanov",
      "count": 2
    },
    {
      "source": "Telegram: RVvoenkor",
      "count": 2
    },
    {
      "source": "Telegram: mezyukho",
      "count": 2
    },
    {
      "source": "Telegram: TheNewOrkTimes",
      "count": 2
    },
    {
      "source": "Telegram: notes_veterans",
      "count": 2
    },
    {
      "source": "Telegram: wargonzo",
      "count": 2
    },
    {
      "source": "Telegram: MIrvMomente",
      "count": 2
    },
    {
      "source": "Telegram: breakingmash",
      "count": 2
    },
    {
      "source": "Telegram: Agdchan",
      "count": 2
    },
    {
      "source": "Telegram: Megatron_ron",
      "count": 2
    },
    {
      "source": "Telegram: rusich_army",
      "count": 2
    },
    {
      "source": "Telegram: skabeeva",
      "count": 2
    },
    {
      "source": "Telegram: intelslava",
      "count": 2
    },
    {
      "source": "Telegram: voicesofrevelation1",
      "count": 2
    },
    {
      "source": "Telegram: militarymaps",
      "count": 1
    },
    {
      "source": "Telegram: CerFunhouse",
      "count": 1
    },
    {
      "source": "Telegram: sskarnaukhov",
      "count": 1
    },
    {
      "source": "Telegram: rt_special",
      "count": 1
    },
    {
      "source": "Telegram: v_odnoy_lodke",
      "count": 1
    },
    {
      "source": "Telegram: voin_dv",
      "count": 1
    },
    {
      "source": "Telegram: georgegalloway",
      "count": 1
    },
    {
      "source": "Telegram: savanichi",
      "count": 1
    },
    {
      "source": "Telegram: segodnia_ru",
      "count": 1
    },
    {
      "source": "Telegram: absatzmedia",
      "count": 1
    },
    {
      "source": "Telegram: soroka_belaya_en",
      "count": 1
    },
    {
      "source": "Telegram: kommunist",
      "count": 1
    },
    {
      "source": "Telegram: eurasiaexpress",
      "count": 1
    },
    {
      "source": "Telegram: politprav",
      "count": 1
    },
    {
      "source": "Telegram: banksta",
      "count": 1
    },
    {
      "source": "Telegram: militarysummary",
      "count": 1
    },
    {
      "source": "Telegram: infodefENGLAND",
      "count": 1
    },
    {
      "source": "Telegram: yourantifakenews",
      "count": 1
    },
    {
      "source": "crimea.ria.ru",
      "count": 1
    },
    {
      "source": "Telegram: MoneroRevolution",
      "count": 1
    },
    {
      "source": "Telegram: IntelRepublic",
      "count": 1
    },
    {
      "source": "Telegram: naspravdiinfo",
      "count": 1
    },
    {
      "source": "Telegram: RIAKremlinpool",
      "count": 1
    },
    {
      "source": "Telegram: media_merkushev",
      "count": 1
    },
    {
      "source": "Telegram: africaninitiative",
      "count": 1
    },
    {
      "source": "Telegram: mig41",
      "count": 1
    },
    {
      "source": "Telegram: apleonkov",
      "count": 1
    },
    {
      "source": "Telegram: wartimedia",
      "count": 1
    },
    {
      "source": "Telegram: artjockey",
      "count": 1
    },
    {
      "source": "Telegram: ScottRitter",
      "count": 1
    },
    {
      "source": "Telegram: zimovskyAL",
      "count": 1
    },
    {
      "source": "Telegram: fsk_today",
      "count": 1
    },
    {
      "source": "Telegram: vladivostok1978",
      "count": 1
    },
    {
      "source": "Telegram: LastOfRus",
      "count": 1
    },
    {
      "source": "Telegram: BFMnews",
      "count": 1
    },
    {
      "source": "Telegram: studentsforIlyin",
      "count": 1
    },
    {
      "source": "Telegram: nwsru",
      "count": 1
    },
    {
      "source": "Telegram: masnoschannel",
      "count": 1
    },
    {
      "source": "Telegram: tavovsky",
      "count": 1
    },
    {
      "source": "Telegram: alexandr_malkevich",
      "count": 1
    },
    {
      "source": "Telegram: panchenkodi",
      "count": 1
    },
    {
      "source": "Telegram: rusengineer",
      "count": 1
    },
    {
      "source": "Telegram: yurasumy",
      "count": 1
    },
    {
      "source": "Telegram: tvcrimea24",
      "count": 1
    },
    {
      "source": "Telegram: BIoomberg",
      "count": 1
    },
    {
      "source": "Telegram: SergeyKolyasnikov",
      "count": 1
    },
    {
      "source": "Telegram: internationalreporters_eng",
      "count": 1
    },
    {
      "source": "Telegram: aklintsevich",
      "count": 1
    },
    {
      "source": "Telegram: readovkanews",
      "count": 1
    },
    {
      "source": "Telegram: russica2",
      "count": 1
    },
    {
      "source": "Telegram: lastoppo",
      "count": 1
    },
    {
      "source": "Telegram: BeornAndTheShieldmaiden",
      "count": 1
    },
    {
      "source": "Telegram: alexbobrowski",
      "count": 1
    },
    {
      "source": "Telegram: belarusian_silovik",
      "count": 1
    },
    {
      "source": "Telegram: milinfolive",
      "count": 1
    },
    {
      "source": "Telegram: izolentalive",
      "count": 1
    },
    {
      "source": "Telegram: selfinvestor",
      "count": 1
    },
    {
      "source": "Telegram: neoficialniybezsonov",
      "count": 1
    },
    {
      "source": "Telegram: zoka200",
      "count": 1
    },
    {
      "source": "Telegram: ramzayiegokomanda",
      "count": 1
    },
    {
      "source": "Telegram: zvezdanews",
      "count": 1
    },
    {
      "source": "Telegram: basurin_e",
      "count": 1
    }
  ],
  "categories": [
    {
      "category": "trump",
      "count": 605
    },
    {
      "category": "world",
      "count": 296
    },
    {
      "category": "ukraine",
      "count": 204
    },
    {
      "category": "russia",
      "count": 177
    }
  ],
  "publicationHours": [
    {
      "hour": 0,
      "count": 33
    },
    {
      "hour": 1,
      "count": 51
    },
    {
      "hour": 2,
      "count": 60
    },
    {
      "hour": 3,
      "count": 69
    },
    {
      "hour": 4,
      "count": 66
    },
    {
      "hour": 5,
      "count": 55
    },
    {
      "hour": 6,
      "count": 51
    },
    {
      "hour": 7,
      "count": 57
    },
    {
      "hour": 8,
      "count": 65
    },
    {
      "hour": 9,
      "count": 73
    },
    {
      "hour": 10,
      "count": 70
    },
    {
      "hour": 11,
      "count": 82
    },
    {
      "hour": 12,
      "count": 74
    },
    {
      "hour": 13,
      "count": 69
    },
    {
      "hour": 14,
      "count": 53
    },
    {
      "hour": 15,
      "count": 60
    },
    {
      "hour": 16,
      "count": 50
    },
    {
      "hour": 17,
      "count": 46
    },
    {
      "hour": 18,
      "count": 43
    },
    {
      "hour": 19,
      "count": 51
    },
    {
      "hour": 20,
      "count": 30
    },
    {
      "hour": 21,
      "count": 31
    },
    {
      "hour": 22,
      "count": 18
    },
    {
      "hour": 23,
      "count": 25
    }
  ],
  "sourcesByDay": [
    {
      "date": "2025-06-06",
      "lenta.ru": 27,
      "kp.ru": 16,
      "tass.ru": 17,
      "ria.ru": 19,
      "russian.rt.com": 21,
      "Telegram: lomovkaa": 8,
      "tsargrad.tv": 9,
      "Telegram: SolovievLive": 9,
      "ren.tv": 14,
      "Telegram: rtnews": 7
    },
    {
      "date": "2025-06-07",
      "lenta.ru": 12,
      "kp.ru": 12,
      "tass.ru": 3,
      "ria.ru": 11,
      "russian.rt.com": 10,
      "Telegram: lomovkaa": 14,
      "tsargrad.tv": 6,
      "Telegram: SolovievLive": 5,
      "ren.tv": 9,
      "Telegram: rtnews": 6
    },
    {
      "date": "2025-06-09",
      "lenta.ru": 9,
      "kp.ru": 14,
      "tass.ru": 7,
      "ria.ru": 9,
      "russian.rt.com": 3,
      "Telegram: lomovkaa": 9,
      "tsargrad.tv": 7,
      "Telegram: SolovievLive": 6,
      "ren.tv": 3,
      "Telegram: rtnews": 2
    },
    {
      "date": "2025-06-10",
      "lenta.ru": 3,
      "kp.ru": 0,
      "tass.ru": 8,
      "ria.ru": 1,
      "russian.rt.com": 1,
      "Telegram: lomovkaa": 4,
      "tsargrad.tv": 3,
      "Telegram: SolovievLive": 3,
      "ren.tv": 2,
      "Telegram: rtnews": 1
    },
    {
      "date": "2025-06-11",
      "lenta.ru": 9,
      "kp.ru": 8,
      "tass.ru": 12,
      "ria.ru": 6,
      "russian.rt.com": 9,
      "Telegram: lomovkaa": 8,
      "tsargrad.tv": 12,
      "Telegram: SolovievLive": 10,
      "ren.tv": 3,
      "Telegram: rtnews": 15
    }
  ],
  "topSourceNames": [
    "lenta.ru",
    "kp.ru",
    "tass.ru",
    "ria.ru",
    "russian.rt.com",
    "Telegram: lomovkaa",
    "tsargrad.tv",
    "Telegram: SolovievLive",
    "ren.tv",
    "Telegram: rtnews"
  ],
  "alternatesStats": {
    "articlesWithAlternates": 1282,
    "percentWithAlternates": 100.0,
    "avgAlternatesPerArticle": 2.562402496099844
  },
  "languages": [
    {
      "language": "en",
      "count": 1711
    },
    {
      "language": "de",
      "count": 64
    },
    {
      "language": "fr",
      "count": 40
    },
    {
      "language": "tr",
      "count": 18
    },
    {
      "language": "hu",
      "count": 14
    },
    {
      "language": "ko",
      "count": 14
    },
    {
      "language": "fi",
      "count": 14
    },
    {
      "language": "ja",
      "count": 14
    },
    {
      "language": "it",
      "count": 12
    },
    {
      "language": "pl",
      "count": 10
    },
    {
      "language": "nl",
      "count": 10
    },
    {
      "language": "et",
      "count": 8
    },
    {
      "language": "ar",
      "count": 6
    },
    {
      "language": "uk",
      "count": 6
    },
    {
      "language": "zh",
      "count": 6
    },
    {
      "language": "lt",
      "count": 6
    },
    {
      "language": "sv",
      "count": 6
    },
    {
      "language": "da",
      "count": 4
    },
    {
      "language": "es",
      "count": 4
    },
    {
      "language": "pt",
      "count": 4
    },
    {
      "language": "ga",
      "count": 4
    },
    {
      "language": "sr",
      "count": 4
    },
    {
      "language": "ro",
      "count": 2
    },
    {
      "language": "hy",
      "count": 2
    },
    {
      "language": "sk",
      "count": 2
    },
    {
      "language": "cs",
      "count": 2
    },
    {
      "language": "no",
      "count": 2
    },
    {
      "language": "lv",
      "count": 2
    },
    {
      "language": "ka",
      "count": 2
    },
    {
      "language": "el",
      "count": 2
    },
    {
      "language": "sq",
      "count": 2
    }
  ],
  "languageConnections": [
    {
      "source": "ro",
      "target": "hy",
      "strength": 1
    },
    {
      "source": "ro",
      "target": "en",
      "strength": 1
    },
    {
      "source": "hy",
      "target": "ro",
      "strength": 1
    },
    {
      "source": "hy",
      "target": "en",
      "strength": 1
    },
    {
      "source": "en",
      "target": "de",
      "strength": 34
    },
    {
      "source": "en",
      "target": "fr",
      "strength": 21
    },
    {
      "source": "en",
      "target": "tr",
      "strength": 9
    },
    {
      "source": "en",
      "target": "hu",
      "strength": 7
    },
    {
      "source": "en",
      "target": "ko",
      "strength": 7
    },
    {
      "source": "en",
      "target": "fi",
      "strength": 7
    },
    {
      "source": "en",
      "target": "ja",
      "strength": 7
    },
    {
      "source": "en",
      "target": "it",
      "strength": 6
    },
    {
      "source": "en",
      "target": "pl",
      "strength": 5
    },
    {
      "source": "en",
      "target": "nl",
      "strength": 5
    },
    {
      "source": "en",
      "target": "et",
      "strength": 4
    },
    {
      "source": "en",
      "target": "sr",
      "strength": 4
    },
    {
      "source": "en",
      "target": "ar",
      "strength": 3
    },
    {
      "source": "en",
      "target": "uk",
      "strength": 3
    },
    {
      "source": "en",
      "target": "zh",
      "strength": 3
    },
    {
      "source": "en",
      "target": "lt",
      "strength": 3
    },
    {
      "source": "en",
      "target": "sv",
      "strength": 3
    },
    {
      "source": "en",
      "target": "da",
      "strength": 2
    },
    {
      "source": "en",
      "target": "pt",
      "strength": 2
    },
    {
      "source": "en",
      "target": "es",
      "strength": 2
    },
    {
      "source": "en",
      "target": "ga",
      "strength": 2
    },
    {
      "source": "en",
      "target": "ro",
      "strength": 1
    },
    {
      "source": "en",
      "target": "hy",
      "strength": 1
    },
    {
      "source": "en",
      "target": "cs",
      "strength": 1
    },
    {
      "source": "en",
      "target": "sk",
      "strength": 1
    },
    {
      "source": "en",
      "target": "no",
      "strength": 1
    },
    {
      "source": "en",
      "target": "lv",
      "strength": 1
    },
    {
      "source": "en",
      "target": "ka",
      "strength": 1
    },
    {
      "source": "en",
      "target": "el",
      "strength": 1
    },
    {
      "source": "en",
      "target": "sq",
      "strength": 1
    },
    {
      "source": "de",
      "target": "en",
      "strength": 34
    },
    {
      "source": "de",
      "target": "fr",
      "strength": 6
    },
    {
      "source": "de",
      "target": "it",
      "strength": 3
    },
    {
      "source": "de",
      "target": "lt",
      "strength": 2
    },
    {
      "source": "de",
      "target": "sr",
      "strength": 2
    },
    {
      "source": "de",
      "target": "ko",
      "strength": 1
    },
    {
      "source": "de",
      "target": "fi",
      "strength": 1
    },
    {
      "source": "de",
      "target": "tr",
      "strength": 1
    },
    {
      "source": "de",
      "target": "pl",
      "strength": 1
    },
    {
      "source": "de",
      "target": "uk",
      "strength": 1
    },
    {
      "source": "de",
      "target": "nl",
      "strength": 1
    },
    {
      "source": "de",
      "target": "et",
      "strength": 1
    },
    {
      "source": "de",
      "target": "lv",
      "strength": 1
    },
    {
      "source": "de",
      "target": "zh",
      "strength": 1
    },
    {
      "source": "de",
      "target": "el",
      "strength": 1
    },
    {
      "source": "de",
      "target": "sq",
      "strength": 1
    },
    {
      "source": "tr",
      "target": "en",
      "strength": 9
    },
    {
      "source": "tr",
      "target": "fr",
      "strength": 2
    },
    {
      "source": "tr",
      "target": "ar",
      "strength": 1
    },
    {
      "source": "tr",
      "target": "sr",
      "strength": 1
    },
    {
      "source": "tr",
      "target": "de",
      "strength": 1
    },
    {
      "source": "fr",
      "target": "en",
      "strength": 21
    },
    {
      "source": "fr",
      "target": "de",
      "strength": 6
    },
    {
      "source": "fr",
      "target": "tr",
      "strength": 2
    },
    {
      "source": "fr",
      "target": "da",
      "strength": 2
    },
    {
      "source": "fr",
      "target": "it",
      "strength": 2
    },
    {
      "source": "fr",
      "target": "pt",
      "strength": 1
    },
    {
      "source": "fr",
      "target": "hu",
      "strength": 1
    },
    {
      "source": "fr",
      "target": "cs",
      "strength": 1
    },
    {
      "source": "fr",
      "target": "pl",
      "strength": 1
    },
    {
      "source": "fr",
      "target": "es",
      "strength": 1
    },
    {
      "source": "fr",
      "target": "sk",
      "strength": 1
    },
    {
      "source": "fr",
      "target": "et",
      "strength": 1
    },
    {
      "source": "fr",
      "target": "ar",
      "strength": 1
    },
    {
      "source": "fr",
      "target": "uk",
      "strength": 1
    },
    {
      "source": "fr",
      "target": "nl",
      "strength": 1
    },
    {
      "source": "fr",
      "target": "zh",
      "strength": 1
    },
    {
      "source": "fr",
      "target": "ja",
      "strength": 1
    },
    {
      "source": "fr",
      "target": "sr",
      "strength": 1
    },
    {
      "source": "fr",
      "target": "el",
      "strength": 1
    },
    {
      "source": "da",
      "target": "fr",
      "strength": 2
    },
    {
      "source": "da",
      "target": "en",
      "strength": 2
    },
    {
      "source": "it",
      "target": "en",
      "strength": 6
    },
    {
      "source": "it",
      "target": "de",
      "strength": 3
    },
    {
      "source": "it",
      "target": "sr",
      "strength": 2
    },
    {
      "source": "it",
      "target": "fr",
      "strength": 2
    },
    {
      "source": "it",
      "target": "ko",
      "strength": 1
    },
    {
      "source": "it",
      "target": "el",
      "strength": 1
    },
    {
      "source": "pt",
      "target": "en",
      "strength": 2
    },
    {
      "source": "pt",
      "target": "es",
      "strength": 2
    },
    {
      "source": "pt",
      "target": "hu",
      "strength": 1
    },
    {
      "source": "pt",
      "target": "cs",
      "strength": 1
    },
    {
      "source": "pt",
      "target": "pl",
      "strength": 1
    },
    {
      "source": "pt",
      "target": "sk",
      "strength": 1
    },
    {
      "source": "pt",
      "target": "fr",
      "strength": 1
    },
    {
      "source": "hu",
      "target": "en",
      "strength": 7
    },
    {
      "source": "hu",
      "target": "pt",
      "strength": 1
    },
    {
      "source": "hu",
      "target": "cs",
      "strength": 1
    },
    {
      "source": "hu",
      "target": "pl",
      "strength": 1
    },
    {
      "source": "hu",
      "target": "es",
      "strength": 1
    },
    {
      "source": "hu",
      "target": "sk",
      "strength": 1
    },
    {
      "source": "hu",
      "target": "fr",
      "strength": 1
    },
    {
      "source": "hu",
      "target": "ko",
      "strength": 1
    },
    {
      "source": "cs",
      "target": "pt",
      "strength": 1
    },
    {
      "source": "cs",
      "target": "hu",
      "strength": 1
    },
    {
      "source": "cs",
      "target": "pl",
      "strength": 1
    },
    {
      "source": "cs",
      "target": "en",
      "strength": 1
    },
    {
      "source": "cs",
      "target": "es",
      "strength": 1
    },
    {
      "source": "cs",
      "target": "sk",
      "strength": 1
    },
    {
      "source": "cs",
      "target": "fr",
      "strength": 1
    },
    {
      "source": "pl",
      "target": "en",
      "strength": 5
    },
    {
      "source": "pl",
      "target": "nl",
      "strength": 2
    },
    {
      "source": "pl",
      "target": "pt",
      "strength": 1
    },
    {
      "source": "pl",
      "target": "hu",
      "strength": 1
    },
    {
      "source": "pl",
      "target": "cs",
      "strength": 1
    },
    {
      "source": "pl",
      "target": "es",
      "strength": 1
    },
    {
      "source": "pl",
      "target": "sk",
      "strength": 1
    },
    {
      "source": "pl",
      "target": "fr",
      "strength": 1
    },
    {
      "source": "pl",
      "target": "ko",
      "strength": 1
    },
    {
      "source": "pl",
      "target": "de",
      "strength": 1
    },
    {
      "source": "pl",
      "target": "lt",
      "strength": 1
    },
    {
      "source": "es",
      "target": "pt",
      "strength": 2
    },
    {
      "source": "es",
      "target": "en",
      "strength": 2
    },
    {
      "source": "es",
      "target": "hu",
      "strength": 1
    },
    {
      "source": "es",
      "target": "cs",
      "strength": 1
    },
    {
      "source": "es",
      "target": "pl",
      "strength": 1
    },
    {
      "source": "es",
      "target": "sk",
      "strength": 1
    },
    {
      "source": "es",
      "target": "fr",
      "strength": 1
    },
    {
      "source": "sk",
      "target": "pt",
      "strength": 1
    },
    {
      "source": "sk",
      "target": "hu",
      "strength": 1
    },
    {
      "source": "sk",
      "target": "cs",
      "strength": 1
    },
    {
      "source": "sk",
      "target": "pl",
      "strength": 1
    },
    {
      "source": "sk",
      "target": "en",
      "strength": 1
    },
    {
      "source": "sk",
      "target": "es",
      "strength": 1
    },
    {
      "source": "sk",
      "target": "fr",
      "strength": 1
    },
    {
      "source": "et",
      "target": "en",
      "strength": 4
    },
    {
      "source": "et",
      "target": "ar",
      "strength": 1
    },
    {
      "source": "et",
      "target": "fr",
      "strength": 1
    },
    {
      "source": "et",
      "target": "lv",
      "strength": 1
    },
    {
      "source": "et",
      "target": "lt",
      "strength": 1
    },
    {
      "source": "et",
      "target": "de",
      "strength": 1
    },
    {
      "source": "et",
      "target": "fi",
      "strength": 1
    },
    {
      "source": "ar",
      "target": "en",
      "strength": 3
    },
    {
      "source": "ar",
      "target": "et",
      "strength": 1
    },
    {
      "source": "ar",
      "target": "fr",
      "strength": 1
    },
    {
      "source": "ar",
      "target": "tr",
      "strength": 1
    },
    {
      "source": "ko",
      "target": "en",
      "strength": 7
    },
    {
      "source": "ko",
      "target": "de",
      "strength": 1
    },
    {
      "source": "ko",
      "target": "pl",
      "strength": 1
    },
    {
      "source": "ko",
      "target": "it",
      "strength": 1
    },
    {
      "source": "ko",
      "target": "sr",
      "strength": 1
    },
    {
      "source": "ko",
      "target": "hu",
      "strength": 1
    },
    {
      "source": "fi",
      "target": "en",
      "strength": 7
    },
    {
      "source": "fi",
      "target": "ja",
      "strength": 2
    },
    {
      "source": "fi",
      "target": "de",
      "strength": 1
    },
    {
      "source": "fi",
      "target": "et",
      "strength": 1
    },
    {
      "source": "uk",
      "target": "en",
      "strength": 3
    },
    {
      "source": "uk",
      "target": "nl",
      "strength": 1
    },
    {
      "source": "uk",
      "target": "de",
      "strength": 1
    },
    {
      "source": "uk",
      "target": "fr",
      "strength": 1
    },
    {
      "source": "ga",
      "target": "en",
      "strength": 2
    },
    {
      "source": "ga",
      "target": "sv",
      "strength": 1
    },
    {
      "source": "sr",
      "target": "en",
      "strength": 4
    },
    {
      "source": "sr",
      "target": "it",
      "strength": 2
    },
    {
      "source": "sr",
      "target": "de",
      "strength": 2
    },
    {
      "source": "sr",
      "target": "tr",
      "strength": 1
    },
    {
      "source": "sr",
      "target": "ko",
      "strength": 1
    },
    {
      "source": "sr",
      "target": "fr",
      "strength": 1
    },
    {
      "source": "sr",
      "target": "sq",
      "strength": 1
    },
    {
      "source": "ja",
      "target": "en",
      "strength": 7
    },
    {
      "source": "ja",
      "target": "fi",
      "strength": 2
    },
    {
      "source": "ja",
      "target": "lt",
      "strength": 1
    },
    {
      "source": "ja",
      "target": "fr",
      "strength": 1
    },
    {
      "source": "zh",
      "target": "en",
      "strength": 3
    },
    {
      "source": "zh",
      "target": "de",
      "strength": 1
    },
    {
      "source": "zh",
      "target": "fr",
      "strength": 1
    },
    {
      "source": "nl",
      "target": "en",
      "strength": 5
    },
    {
      "source": "nl",
      "target": "pl",
      "strength": 2
    },
    {
      "source": "nl",
      "target": "uk",
      "strength": 1
    },
    {
      "source": "nl",
      "target": "de",
      "strength": 1
    },
    {
      "source": "nl",
      "target": "fr",
      "strength": 1
    },
    {
      "source": "lt",
      "target": "en",
      "strength": 3
    },
    {
      "source": "lt",
      "target": "de",
      "strength": 2
    },
    {
      "source": "lt",
      "target": "pl",
      "strength": 1
    },
    {
      "source": "lt",
      "target": "ja",
      "strength": 1
    },
    {
      "source": "lt",
      "target": "et",
      "strength": 1
    },
    {
      "source": "lt",
      "target": "lv",
      "strength": 1
    },
    {
      "source": "no",
      "target": "en",
      "strength": 1
    },
    {
      "source": "lv",
      "target": "et",
      "strength": 1
    },
    {
      "source": "lv",
      "target": "lt",
      "strength": 1
    },
    {
      "source": "lv",
      "target": "en",
      "strength": 1
    },
    {
      "source": "lv",
      "target": "de",
      "strength": 1
    },
    {
      "source": "ka",
      "target": "en",
      "strength": 1
    },
    {
      "source": "sv",
      "target": "en",
      "strength": 3
    },
    {
      "source": "sv",
      "target": "ga",
      "strength": 1
    },
    {
      "source": "el",
      "target": "it",
      "strength": 1
    },
    {
      "source": "el",
      "target": "en",
      "strength": 1
    },
    {
      "source": "el",
      "target": "de",
      "strength": 1
    },
    {
      "source": "el",
      "target": "fr",
      "strength": 1
    },
    {
      "source": "sq",
      "target": "de",
      "strength": 1
    },
    {
      "source": "sq",
      "target": "sr",
      "strength": 1
    },
    {
      "source": "sq",
      "target": "en",
      "strength": 1
    }
  ],
  "domainLanguageData": [
    {
      "domain": "trump.news-pravda.com",
      "language": "en",
      "count": 742
    },
    {
      "domain": "usa.news-pravda.com",
      "language": "en",
      "count": 701
    },
    {
      "domain": "turkey.news-pravda.com",
      "language": "en",
      "count": 14
    },
    {
      "domain": "turkey.news-pravda.com",
      "language": "tr",
      "count": 18
    },
    {
      "domain": "italy.news-pravda.com",
      "language": "en",
      "count": 9
    },
    {
      "domain": "italy.news-pravda.com",
      "language": "it",
      "count": 12
    },
    {
      "domain": "germany.news-pravda.com",
      "language": "en",
      "count": 50
    },
    {
      "domain": "germany.news-pravda.com",
      "language": "de",
      "count": 30
    },
    {
      "domain": "md.news-pravda.com",
      "language": "en",
      "count": 1
    },
    {
      "domain": "md.news-pravda.com",
      "language": "ro",
      "count": 2
    },
    {
      "domain": "armenia.news-pravda.com",
      "language": "hy",
      "count": 2
    },
    {
      "domain": "armenia.news-pravda.com",
      "language": "en",
      "count": 1
    },
    {
      "domain": "deutsch.news-pravda.com",
      "language": "de",
      "count": 28
    },
    {
      "domain": "canada.news-pravda.com",
      "language": "fr",
      "count": 12
    },
    {
      "domain": "canada.news-pravda.com",
      "language": "en",
      "count": 14
    },
    {
      "domain": "ua.news-pravda.com",
      "language": "en",
      "count": 12
    },
    {
      "domain": "ua.news-pravda.com",
      "language": "uk",
      "count": 6
    },
    {
      "domain": "denmark.news-pravda.com",
      "language": "en",
      "count": 3
    },
    {
      "domain": "denmark.news-pravda.com",
      "language": "da",
      "count": 4
    },
    {
      "domain": "france.news-pravda.com",
      "language": "fr",
      "count": 13
    },
    {
      "domain": "france.news-pravda.com",
      "language": "en",
      "count": 15
    },
    {
      "domain": "francais.news-pravda.com",
      "language": "fr",
      "count": 11
    },
    {
      "domain": "spain.news-pravda.com",
      "language": "es",
      "count": 3
    },
    {
      "domain": "spain.news-pravda.com",
      "language": "en",
      "count": 2
    },
    {
      "domain": "portuguese.news-pravda.com",
      "language": "pt",
      "count": 2
    },
    {
      "domain": "hungary.news-pravda.com",
      "language": "hu",
      "count": 14
    },
    {
      "domain": "hungary.news-pravda.com",
      "language": "en",
      "count": 8
    },
    {
      "domain": "uk.news-pravda.com",
      "language": "en",
      "count": 38
    },
    {
      "domain": "portugal.news-pravda.com",
      "language": "en",
      "count": 2
    },
    {
      "domain": "portugal.news-pravda.com",
      "language": "pt",
      "count": 2
    },
    {
      "domain": "poland.news-pravda.com",
      "language": "en",
      "count": 9
    },
    {
      "domain": "poland.news-pravda.com",
      "language": "pl",
      "count": 10
    },
    {
      "domain": "slovakia.news-pravda.com",
      "language": "sk",
      "count": 2
    },
    {
      "domain": "slovakia.news-pravda.com",
      "language": "en",
      "count": 1
    },
    {
      "domain": "czechia.news-pravda.com",
      "language": "en",
      "count": 2
    },
    {
      "domain": "czechia.news-pravda.com",
      "language": "cs",
      "count": 2
    },
    {
      "domain": "algeria.news-pravda.com",
      "language": "ar",
      "count": 2
    },
    {
      "domain": "algeria.news-pravda.com",
      "language": "en",
      "count": 1
    },
    {
      "domain": "estonia.news-pravda.com",
      "language": "en",
      "count": 4
    },
    {
      "domain": "estonia.news-pravda.com",
      "language": "et",
      "count": 8
    },
    {
      "domain": "south-korea.news-pravda.com",
      "language": "ko",
      "count": 4
    },
    {
      "domain": "south-korea.news-pravda.com",
      "language": "en",
      "count": 4
    },
    {
      "domain": "korea.news-pravda.com",
      "language": "ko",
      "count": 7
    },
    {
      "domain": "finland.news-pravda.com",
      "language": "en",
      "count": 9
    },
    {
      "domain": "finland.news-pravda.com",
      "language": "fi",
      "count": 14
    },
    {
      "domain": "eritrea.news-pravda.com",
      "language": "ar",
      "count": 2
    },
    {
      "domain": "dprk.news-pravda.com",
      "language": "ko",
      "count": 3
    },
    {
      "domain": "dprk.news-pravda.com",
      "language": "en",
      "count": 4
    },
    {
      "domain": "syria.news-pravda.com",
      "language": "ar",
      "count": 2
    },
    {
      "domain": "syria.news-pravda.com",
      "language": "en",
      "count": 2
    },
    {
      "domain": "ireland.news-pravda.com",
      "language": "ga",
      "count": 4
    },
    {
      "domain": "ireland.news-pravda.com",
      "language": "en",
      "count": 2
    },
    {
      "domain": "balkan.news-pravda.com",
      "language": "sr",
      "count": 4
    },
    {
      "domain": "japan.news-pravda.com",
      "language": "ja",
      "count": 14
    },
    {
      "domain": "japan.news-pravda.com",
      "language": "en",
      "count": 7
    },
    {
      "domain": "switzerland.news-pravda.com",
      "language": "fr",
      "count": 4
    },
    {
      "domain": "switzerland.news-pravda.com",
      "language": "en",
      "count": 6
    },
    {
      "domain": "switzerland.news-pravda.com",
      "language": "de",
      "count": 2
    },
    {
      "domain": "serbia.news-pravda.com",
      "language": "en",
      "count": 3
    },
    {
      "domain": "netherlands.news-pravda.com",
      "language": "en",
      "count": 6
    },
    {
      "domain": "netherlands.news-pravda.com",
      "language": "nl",
      "count": 5
    },
    {
      "domain": "taiwan.news-pravda.com",
      "language": "zh",
      "count": 6
    },
    {
      "domain": "taiwan.news-pravda.com",
      "language": "en",
      "count": 3
    },
    {
      "domain": "au.news-pravda.com",
      "language": "en",
      "count": 13
    },
    {
      "domain": "dutch.news-pravda.com",
      "language": "nl",
      "count": 5
    },
    {
      "domain": "mali.news-pravda.com",
      "language": "en",
      "count": 1
    },
    {
      "domain": "south-sudan.news-pravda.com",
      "language": "en",
      "count": 1
    },
    {
      "domain": "romania.news-pravda.com",
      "language": "en",
      "count": 2
    },
    {
      "domain": "lt.news-pravda.com",
      "language": "lt",
      "count": 6
    },
    {
      "domain": "lt.news-pravda.com",
      "language": "en",
      "count": 1
    },
    {
      "domain": "rca.news-pravda.com",
      "language": "en",
      "count": 5
    },
    {
      "domain": "norway.news-pravda.com",
      "language": "no",
      "count": 2
    },
    {
      "domain": "norway.news-pravda.com",
      "language": "en",
      "count": 1
    },
    {
      "domain": "latvia.news-pravda.com",
      "language": "en",
      "count": 1
    },
    {
      "domain": "latvia.news-pravda.com",
      "language": "lv",
      "count": 2
    },
    {
      "domain": "ge.news-pravda.com",
      "language": "en",
      "count": 1
    },
    {
      "domain": "ge.news-pravda.com",
      "language": "ka",
      "count": 2
    },
    {
      "domain": "spanish.news-pravda.com",
      "language": "es",
      "count": 1
    },
    {
      "domain": "austria.news-pravda.com",
      "language": "en",
      "count": 3
    },
    {
      "domain": "austria.news-pravda.com",
      "language": "de",
      "count": 4
    },
    {
      "domain": "sweden.news-pravda.com",
      "language": "en",
      "count": 3
    },
    {
      "domain": "sweden.news-pravda.com",
      "language": "sv",
      "count": 6
    },
    {
      "domain": "greece.news-pravda.com",
      "language": "el",
      "count": 2
    },
    {
      "domain": "greece.news-pravda.com",
      "language": "en",
      "count": 1
    },
    {
      "domain": "singapore.news-pravda.com",
      "language": "en",
      "count": 2
    },
    {
      "domain": "albania.news-pravda.com",
      "language": "en",
      "count": 1
    },
    {
      "domain": "albania.news-pravda.com",
      "language": "sq",
      "count": 2
    }
  ],
  "countryLanguageData": [
    {
      "code": "en",
      "count": 742
    },
    {
      "code": "en-US",
      "count": 701
    },
    {
      "code": "en-DE",
      "count": 50
    },
    {
      "code": "en-GB",
      "count": 38
    },
    {
      "code": "de",
      "count": 34
    },
    {
      "code": "de-DE",
      "count": 25
    },
    {
      "code": "fr",
      "count": 21
    },
    {
      "code": "en-FR",
      "count": 15
    },
    {
      "code": "en-TR",
      "count": 14
    },
    {
      "code": "en-CA",
      "count": 14
    },
    {
      "code": "en-AU",
      "count": 13
    },
    {
      "code": "en-UA",
      "count": 12
    },
    {
      "code": "fr-FR",
      "count": 11
    },
    {
      "code": "en-IT",
      "count": 9
    },
    {
      "code": "tr-TR",
      "count": 9
    },
    {
      "code": "tr",
      "count": 9
    },
    {
      "code": "en-PL",
      "count": 9
    },
    {
      "code": "en-FI",
      "count": 9
    },
    {
      "code": "en-HU",
      "count": 8
    },
    {
      "code": "hu-HU",
      "count": 7
    },
    {
      "code": "hu",
      "count": 7
    },
    {
      "code": "ko",
      "count": 7
    },
    {
      "code": "fi-FI",
      "count": 7
    },
    {
      "code": "fi",
      "count": 7
    },
    {
      "code": "ja-JP",
      "count": 7
    },
    {
      "code": "en-JP",
      "count": 7
    },
    {
      "code": "ja",
      "count": 7
    },
    {
      "code": "fr-CA",
      "count": 6
    },
    {
      "code": "it-IT",
      "count": 6
    },
    {
      "code": "it",
      "count": 6
    },
    {
      "code": "en-CH",
      "count": 6
    },
    {
      "code": "en-NL",
      "count": 6
    },
    {
      "code": "pl-PL",
      "count": 5
    },
    {
      "code": "pl",
      "count": 5
    },
    {
      "code": "nl-NL",
      "count": 5
    },
    {
      "code": "nl",
      "count": 5
    },
    {
      "code": "en-CF",
      "count": 5
    },
    {
      "code": "en-EE",
      "count": 4
    },
    {
      "code": "et-EE",
      "count": 4
    },
    {
      "code": "et",
      "count": 4
    },
    {
      "code": "ko-KR",
      "count": 4
    },
    {
      "code": "en-KR",
      "count": 4
    },
    {
      "code": "en-KP",
      "count": 4
    },
    {
      "code": "sr",
      "count": 4
    },
    {
      "code": "en-DK",
      "count": 3
    },
    {
      "code": "ar",
      "count": 3
    },
    {
      "code": "ko-KP",
      "count": 3
    },
    {
      "code": "uk-UA",
      "count": 3
    },
    {
      "code": "uk",
      "count": 3
    },
    {
      "code": "en-RS",
      "count": 3
    },
    {
      "code": "zh-TW",
      "count": 3
    },
    {
      "code": "en-TW",
      "count": 3
    },
    {
      "code": "zh",
      "count": 3
    },
    {
      "code": "lt-LT",
      "count": 3
    },
    {
      "code": "lt",
      "count": 3
    },
    {
      "code": "en-AT",
      "count": 3
    },
    {
      "code": "de-AT",
      "count": 3
    },
    {
      "code": "en-SE",
      "count": 3
    },
    {
      "code": "sv-SE",
      "count": 3
    },
    {
      "code": "sv",
      "count": 3
    },
    {
      "code": "da-DK",
      "count": 2
    },
    {
      "code": "da",
      "count": 2
    },
    {
      "code": "es-ES",
      "count": 2
    },
    {
      "code": "pt",
      "count": 2
    },
    {
      "code": "en-PT",
      "count": 2
    },
    {
      "code": "en-CZ",
      "count": 2
    },
    {
      "code": "pt-PT",
      "count": 2
    },
    {
      "code": "en-ES",
      "count": 2
    },
    {
      "code": "es",
      "count": 2
    },
    {
      "code": "en-SY",
      "count": 2
    },
    {
      "code": "ga-IE",
      "count": 2
    },
    {
      "code": "en-IE",
      "count": 2
    },
    {
      "code": "ga",
      "count": 2
    },
    {
      "code": "fr-CH",
      "count": 2
    },
    {
      "code": "de-CH",
      "count": 2
    },
    {
      "code": "en-RO",
      "count": 2
    },
    {
      "code": "en-SG",
      "count": 2
    },
    {
      "code": "en-MD",
      "count": 1
    },
    {
      "code": "ro-MD",
      "count": 1
    },
    {
      "code": "hy-AM",
      "count": 1
    },
    {
      "code": "en-AM",
      "count": 1
    },
    {
      "code": "ro",
      "count": 1
    },
    {
      "code": "hy",
      "count": 1
    },
    {
      "code": "sk-SK",
      "count": 1
    },
    {
      "code": "en-SK",
      "count": 1
    },
    {
      "code": "cs-CZ",
      "count": 1
    },
    {
      "code": "sk",
      "count": 1
    },
    {
      "code": "cs",
      "count": 1
    },
    {
      "code": "ar-DZ",
      "count": 1
    },
    {
      "code": "en-DZ",
      "count": 1
    },
    {
      "code": "ar-ER",
      "count": 1
    },
    {
      "code": "ar-SY",
      "count": 1
    },
    {
      "code": "en-ML",
      "count": 1
    },
    {
      "code": "en-SS",
      "count": 1
    },
    {
      "code": "no-NO",
      "count": 1
    },
    {
      "code": "en-NO",
      "count": 1
    },
    {
      "code": "no",
      "count": 1
    },
    {
      "code": "en-LT",
      "count": 1
    },
    {
      "code": "en-LV",
      "count": 1
    },
    {
      "code": "lv-LV",
      "count": 1
    },
    {
      "code": "lv",
      "count": 1
    },
    {
      "code": "en-GE",
      "count": 1
    },
    {
      "code": "ka-GE",
      "count": 1
    },
    {
      "code": "ka",
      "count": 1
    },
    {
      "code": "el-GR",
      "count": 1
    },
    {
      "code": "en-GR",
      "count": 1
    },
    {
      "code": "el",
      "count": 1
    },
    {
      "code": "en-AL",
      "count": 1
    },
    {
      "code": "sq-AL",
      "count": 1
    },
    {
      "code": "sq",
      "count": 1
    }
  ],
  "allDomains": [
    "francais.news-pravda.com",
    "ua.news-pravda.com",
    "norway.news-pravda.com",
    "denmark.news-pravda.com",
    "korea.news-pravda.com",
    "deutsch.news-pravda.com",
    "ireland.news-pravda.com",
    "austria.news-pravda.com",
    "albania.news-pravda.com",
    "estonia.news-pravda.com",
    "south-korea.news-pravda.com",
    "mali.news-pravda.com",
    "balkan.news-pravda.com",
    "ge.news-pravda.com",
    "czechia.news-pravda.com",
    "hungary.news-pravda.com",
    "latvia.news-pravda.com",
    "south-sudan.news-pravda.com",
    "slovakia.news-pravda.com",
    "portugal.news-pravda.com",
    "dprk.news-pravda.com",
    "syria.news-pravda.com",
    "serbia.news-pravda.com",
    "netherlands.news-pravda.com",
    "romania.news-pravda.com",
    "turkey.news-pravda.com",
    "japan.news-pravda.com",
    "france.news-pravda.com",
    "md.news-pravda.com",
    "canada.news-pravda.com",
    "algeria.news-pravda.com",
    "au.news-pravda.com",
    "italy.news-pravda.com",
    "spanish.news-pravda.com",
    "switzerland.news-pravda.com",
    "taiwan.news-pravda.com",
    "sweden.news-pravda.com",
    "eritrea.news-pravda.com",
    "rca.news-pravda.com",
    "poland.news-pravda.com",
    "trump.news-pravda.com",
    "dutch.news-pravda.com",
    "germany.news-pravda.com",
    "portuguese.news-pravda.com",
    "uk.news-pravda.com",
    "spain.news-pravda.com",
    "finland.news-pravda.com",
    "lt.news-pravda.com",
    "usa.news-pravda.com",
    "singapore.news-pravda.com",
    "armenia.news-pravda.com",
    "greece.news-pravda.com"
  ],
  "allLanguages": [
    "ro",
    "sr",
    "sq",
    "lv",
    "it",
    "cs",
    "hu",
    "ko",
    "pl",
    "fi",
    "ar",
    "es",
    "de",
    "zh",
    "sk",
    "pt",
    "et",
    "uk",
    "tr",
    "no",
    "ja",
    "ka",
    "sv",
    "fr",
    "da",
    "ga",
    "nl",
    "lt",
    "en",
    "hy",
    "el"
  ]
}